{
  "title": "Mixed Problems",
  "description": "A collection of basic arithmetic problems covering integers, decimals, and fractions, increasing in difficulty across five waves. All mathematical expressions are rendered using LaTeX.",
  "waves": 5,
  "timePerQuestion": 30,
  "questions": [
    {
      "id": 1,
      "wave": 1,
      "question": "$6.77 \\div \\frac{3}{8}$",
      "choices": ["21.71", "14.36", "18.053", "16.16"],
      "answer": "18.053",
      "points": 10
    },
    {
      "id": 2,
      "wave": 1,
      "question": "$3 + 8$",
      "choices": ["6.19", "11", "15.03", "8.5"],
      "answer": "11",
      "points": 10
    },
    {
      "id": 3,
      "wave": 1,
      "question": "$9.09 + 8$",
      "choices": ["14.58", "17.09", "12.19", "17.38"],
      "answer": "17.09",
      "points": 10
    },
    {
      "id": 4,
      "wave": 1,
      "question": "$4 \\div 4$",
      "choices": ["4.34", "2.93", "1", "-0.59"],
      "answer": "1",
      "points": 10
    },
    {
      "id": 5,
      "wave": 1,
      "question": "$8.35 + 3$",
      "choices": ["11.35", "9.25", "13.3", "12.06"],
      "answer": "11.35",
      "points": 10
    },
    {
      "id": 6,
      "wave": 1,
      "question": "$6 + 9.17$",
      "choices": ["16.92", "11.54", "15.54", "15.17"],
      "answer": "15.17",
      "points": 10
    },
    {
      "id": 7,
      "wave": 1,
      "question": "$2.95 \\times 7.88$",
      "choices": ["23.246", "22.65", "18.77", "27.84"],
      "answer": "23.246",
      "points": 10
    },
    {
      "id": 8,
      "wave": 1,
      "question": "$7.22 - 10$",
      "choices": ["1.82", "-4.86", "-2.78", "-3.39"],
      "answer": "-2.78",
      "points": 10
    },
    {
      "id": 9,
      "wave": 1,
      "question": "$6 \\div 6$",
      "choices": ["1", "-0.05", "5.12", "5.94"],
      "answer": "1",
      "points": 10
    },
    {
      "id": 10,
      "wave": 1,
      "question": "$\\frac{7}{10} + 2$",
      "choices": ["2.7", "6.19", "4.83", "-0.56"],
      "answer": "2.7",
      "points": 10
    },
    {
      "id": 11,
      "wave": 1,
      "question": "$1.41 \\times 6.7$",
      "choices": ["7.09", "9.447", "8.31", "7.68"],
      "answer": "9.447",
      "points": 10
    },
    {
      "id": 12,
      "wave": 1,
      "question": "$6 \\div 2.87$",
      "choices": ["0.93", "2.091", "0.37", "-1.98"],
      "answer": "2.091",
      "points": 10
    },
    {
      "id": 13,
      "wave": 1,
      "question": "$1 + 9.21$",
      "choices": ["10.21", "9.27", "10.35", "7.04"],
      "answer": "10.21",
      "points": 10
    },
    {
      "id": 14,
      "wave": 1,
      "question": "$4 + 8$",
      "choices": ["15.73", "12", "15.19", "12.82"],
      "answer": "12",
      "points": 10
    },
    {
      "id": 15,
      "wave": 1,
      "question": "$9.83 - 7$",
      "choices": ["2.52", "-0.7", "3.68", "2.83"],
      "answer": "2.83",
      "points": 10
    },
    {
      "id": 16,
      "wave": 1,
      "question": "$8 \\div \\frac{3}{8}$",
      "choices": ["21.333", "21.65", "18.79", "25.34"],
      "answer": "21.333",
      "points": 10
    },
    {
      "id": 17,
      "wave": 1,
      "question": "$6 - 9$",
      "choices": ["-5.88", "-2.28", "-5.28", "-3"],
      "answer": "-3",
      "points": 10
    },
    {
      "id": 18,
      "wave": 1,
      "question": "$\\frac{9}{10} \\times 4.33$",
      "choices": ["3.897", "8.4", "2.19", "1.82"],
      "answer": "3.897",
      "points": 10
    },
    {
      "id": 19,
      "wave": 1,
      "question": "$2 \\times 7$",
      "choices": ["15.23", "14", "11.18", "10.04"],
      "answer": "14",
      "points": 10
    },
    {
      "id": 20,
      "wave": 1,
      "question": "$\\frac{6}{5} + 7.85$",
      "choices": ["10.6", "4.91", "4.94", "9.05"],
      "answer": "9.05",
      "points": 10
    },
    {
      "id": 21,
      "wave": 1,
      "question": "$\\frac{1}{7} \\div 9$",
      "choices": ["-4.63", "-1.71", "-3.08", "0.016"],
      "answer": "0.016",
      "points": 10
    },
    {
      "id": 22,
      "wave": 1,
      "question": "$\\frac{1}{2} \\times 10$",
      "choices": ["6.21", "9.69", "1.58", "5"],
      "answer": "5",
      "points": 10
    },
    {
      "id": 23,
      "wave": 1,
      "question": "$1.21 + 5$",
      "choices": ["4.34", "4.71", "10.78", "6.21"],
      "answer": "6.21",
      "points": 10
    },
    {
      "id": 24,
      "wave": 1,
      "question": "$4 + 10$",
      "choices": ["18.96", "14", "13.57", "15.75"],
      "answer": "14",
      "points": 10
    },
    {
      "id": 25,
      "wave": 1,
      "question": "$1 \\div 9$",
      "choices": ["2.03", "-4.63", "2.48", "0.111"],
      "answer": "0.111",
      "points": 10
    },
    {
      "id": 26,
      "wave": 1,
      "question": "$1 + \\frac{1}{5}$",
      "choices": ["0.75", "1.2", "-2.74", "4.47"],
      "answer": "1.2",
      "points": 10
    },
    {
      "id": 27,
      "wave": 1,
      "question": "$4 - 6.26$",
      "choices": ["-6.92", "2.66", "-0.91", "-2.26"],
      "answer": "-2.26",
      "points": 10
    },
    {
      "id": 28,
      "wave": 1,
      "question": "$\\frac{2}{9} + 2$",
      "choices": ["4.05", "-1.53", "2.69", "2.222"],
      "answer": "2.222",
      "points": 10
    },
    {
      "id": 29,
      "wave": 1,
      "question": "$\\frac{9}{4} - 3$",
      "choices": ["-0.75", "-4.87", "-5.35", "-1.9"],
      "answer": "-0.75",
      "points": 10
    },
    {
      "id": 30,
      "wave": 1,
      "question": "$2.69 \\div \\frac{1}{2}$",
      "choices": ["6.56", "6.95", "8.92", "5.38"],
      "answer": "5.38",
      "points": 10
    },
    {
      "id": 31,
      "wave": 1,
      "question": "$\\frac{7}{10} + 2.52$",
      "choices": ["7.06", "5.83", "5.21", "3.22"],
      "answer": "3.22",
      "points": 10
    },
    {
      "id": 32,
      "wave": 1,
      "question": "$\\frac{3}{10} - 7.43$",
      "choices": ["-6.03", "-8.94", "-7.13", "-7.73"],
      "answer": "-7.13",
      "points": 10
    },
    {
      "id": 33,
      "wave": 1,
      "question": "$10 - 4$",
      "choices": ["3.22", "2.35", "4.66", "6"],
      "answer": "6",
      "points": 10
    },
    {
      "id": 34,
      "wave": 1,
      "question": "$8.06 - 7.13$",
      "choices": ["3.93", "0.93", "2.59", "5.41"],
      "answer": "0.93",
      "points": 10
    },
    {
      "id": 35,
      "wave": 1,
      "question": "$8.33 - \\frac{3}{10}$",
      "choices": ["3.35", "8.36", "10.82", "8.03"],
      "answer": "8.03",
      "points": 10
    },
    {
      "id": 36,
      "wave": 1,
      "question": "$\\frac{5}{8} \\div 4$",
      "choices": ["1.52", "4.89", "-1.68", "0.156"],
      "answer": "0.156",
      "points": 10
    },
    {
      "id": 37,
      "wave": 1,
      "question": "$2.19 + \\frac{9}{5}$",
      "choices": ["3.99", "5.55", "2.73", "2.24"],
      "answer": "3.99",
      "points": 10
    },
    {
      "id": 38,
      "wave": 1,
      "question": "$5 - 4.11$",
      "choices": ["-1.85", "1.18", "-0.02", "0.89"],
      "answer": "0.89",
      "points": 10
    },
    {
      "id": 39,
      "wave": 1,
      "question": "$\\frac{4}{7} + \\frac{3}{10}$",
      "choices": ["-2.52", "2.41", "0.871", "3.66"],
      "answer": "0.871",
      "points": 10
    },
    {
      "id": 40,
      "wave": 1,
      "question": "$8.61 + 10$",
      "choices": ["18.49", "18.92", "13.71", "18.61"],
      "answer": "18.61",
      "points": 10
    },
    {
      "id": 41,
      "wave": 1,
      "question": "$6 \\times \\frac{7}{9}$",
      "choices": ["5.43", "4.667", "5.01", "7.28"],
      "answer": "4.667",
      "points": 10
    },
    {
      "id": 42,
      "wave": 1,
      "question": "$\\frac{6}{5} + \\frac{2}{3}$",
      "choices": ["-2.42", "1.867", "5.3", "4.35"],
      "answer": "1.867",
      "points": 10
    },
    {
      "id": 43,
      "wave": 1,
      "question": "$\\frac{1}{5} - \\frac{2}{3}$",
      "choices": ["-3.63", "0.6", "-0.467", "4.36"],
      "answer": "-0.467",
      "points": 10
    },
    {
      "id": 44,
      "wave": 1,
      "question": "$\\frac{5}{7} \\div \\frac{3}{7}$",
      "choices": ["5.71", "4.56", "1.667", "4.39"],
      "answer": "1.667",
      "points": 10
    },
    {
      "id": 45,
      "wave": 1,
      "question": "$7 - 2.91$",
      "choices": ["4.09", "8", "7.93", "-0.23"],
      "answer": "4.09",
      "points": 10
    },
    {
      "id": 46,
      "wave": 1,
      "question": "$8 + \\frac{8}{7}$",
      "choices": ["10.36", "9.143", "13.39", "13.97"],
      "answer": "9.143",
      "points": 10
    },
    {
      "id": 47,
      "wave": 1,
      "question": "$\\frac{2}{5} \\times 5.97$",
      "choices": ["4.66", "2.388", "1.11", "-1.88"],
      "answer": "2.388",
      "points": 10
    },
    {
      "id": 48,
      "wave": 1,
      "question": "$4.25 - \\frac{2}{5}$",
      "choices": ["-0.09", "3.85", "4.31", "7.42"],
      "answer": "3.85",
      "points": 10
    },
    {
      "id": 49,
      "wave": 1,
      "question": "$8.21 \\times \\frac{3}{4}$",
      "choices": ["6.158", "7.35", "1.96", "1.76"],
      "answer": "6.158",
      "points": 10
    },
    {
      "id": 50,
      "wave": 1,
      "question": "$5.03 \\div 4$",
      "choices": ["3.31", "1.258", "3.86", "-0.22"],
      "answer": "1.258",
      "points": 10
    },
    {
      "id": 51,
      "wave": 2,
      "question": "$6.66 \\div \\frac{1}{3}$",
      "choices": ["15.83", "19.98", "23.95", "16.79"],
      "answer": "19.98",
      "points": 15
    },
    {
      "id": 52,
      "wave": 2,
      "question": "$4 \\times 9.47$",
      "choices": ["37.88", "36.95", "34.84", "38.05"],
      "answer": "37.88",
      "points": 15
    },
    {
      "id": 53,
      "wave": 2,
      "question": "$2 \\div \\frac{3}{2}$",
      "choices": ["4.6", "5.64", "-3.22", "1.333"],
      "answer": "1.333",
      "points": 15
    },
    {
      "id": 54,
      "wave": 2,
      "question": "$8 \\div 10.17$",
      "choices": ["0.65", "0.787", "-1.38", "-2.8"],
      "answer": "0.787",
      "points": 15
    },
    {
      "id": 55,
      "wave": 2,
      "question": "$11 + 3.65$",
      "choices": ["11.68", "12.53", "14.65", "13.58"],
      "answer": "14.65",
      "points": 15
    },
    {
      "id": 56,
      "wave": 2,
      "question": "$18 + 6.23$",
      "choices": ["27.81", "23.01", "25.39", "24.23"],
      "answer": "24.23",
      "points": 15
    },
    {
      "id": 57,
      "wave": 2,
      "question": "$5.37 - \\frac{5}{7}$",
      "choices": ["5.46", "4.656", "-0.09", "3.37"],
      "answer": "4.656",
      "points": 15
    },
    {
      "id": 58,
      "wave": 2,
      "question": "$2.64 - 13$",
      "choices": ["-10.36", "-11.76", "-14.4", "-8.2"],
      "answer": "-10.36",
      "points": 15
    },
    {
      "id": 59,
      "wave": 2,
      "question": "$\\frac{5}{4} - \\frac{5}{8}$",
      "choices": ["0.625", "-0.42", "2.09", "-2.56"],
      "answer": "0.625",
      "points": 15
    },
    {
      "id": 60,
      "wave": 2,
      "question": "$16.51 - 13$",
      "choices": ["3.51", "-0.95", "-0.29", "-0.21"],
      "answer": "3.51",
      "points": 15
    },
    {
      "id": 61,
      "wave": 2,
      "question": "$1 + 7.11$",
      "choices": ["8.11", "11.37", "10.91", "12.34"],
      "answer": "8.11",
      "points": 15
    },
    {
      "id": 62,
      "wave": 2,
      "question": "$\\frac{11}{2} + 9$",
      "choices": ["14.5", "12.56", "13.3", "10.08"],
      "answer": "14.5",
      "points": 15
    },
    {
      "id": 63,
      "wave": 2,
      "question": "$\\frac{5}{6} - \\frac{1}{4}$",
      "choices": ["0.583", "3.53", "3.03", "-0.97"],
      "answer": "0.583",
      "points": 15
    },
    {
      "id": 64,
      "wave": 2,
      "question": "$\\frac{1}{10} + 17$",
      "choices": ["16.75", "17.32", "17.1", "20.58"],
      "answer": "17.1",
      "points": 15
    },
    {
      "id": 65,
      "wave": 2,
      "question": "$2 \\times \\frac{4}{9}$",
      "choices": ["3.87", "0.889", "3.31", "-3.89"],
      "answer": "0.889",
      "points": 15
    },
    {
      "id": 66,
      "wave": 2,
      "question": "$17 \\div 17$",
      "choices": ["5.44", "1", "-3.31", "2.24"],
      "answer": "1",
      "points": 15
    },
    {
      "id": 67,
      "wave": 2,
      "question": "$13 \\div 11.18$",
      "choices": ["1.163", "-2.42", "-3.67", "-1.45"],
      "answer": "1.163",
      "points": 15
    },
    {
      "id": 68,
      "wave": 2,
      "question": "$0 \\div 1$",
      "choices": ["4.53", "0", "3.39", "-1.4"],
      "answer": "0",
      "points": 15
    },
    {
      "id": 69,
      "wave": 2,
      "question": "$10.31 + 5.47$",
      "choices": ["19.86", "15.78", "14.09", "17.4"],
      "answer": "15.78",
      "points": 15
    },
    {
      "id": 70,
      "wave": 2,
      "question": "$\\frac{13}{8} + 19.95$",
      "choices": ["26.2", "23.46", "24.39", "21.575"],
      "answer": "21.575",
      "points": 15
    },
    {
      "id": 71,
      "wave": 2,
      "question": "$\\frac{2}{5} - \\frac{6}{5}$",
      "choices": ["-1.7", "-0.8", "-1.06", "-3.15"],
      "answer": "-0.8",
      "points": 15
    },
    {
      "id": 72,
      "wave": 2,
      "question": "$2 \\times 8.71$",
      "choices": ["18.41", "17.42", "13.81", "15.4"],
      "answer": "17.42",
      "points": 15
    },
    {
      "id": 73,
      "wave": 2,
      "question": "$17.35 + \\frac{11}{5}$",
      "choices": ["19.55", "23.83", "21.06", "23.15"],
      "answer": "19.55",
      "points": 15
    },
    {
      "id": 74,
      "wave": 2,
      "question": "$17.97 \\times 3$",
      "choices": ["51.69", "49.37", "53.91", "49.36"],
      "answer": "53.91",
      "points": 15
    },
    {
      "id": 75,
      "wave": 2,
      "question": "$12 - \\frac{2}{9}$",
      "choices": ["15.61", "8.76", "11.778", "14.06"],
      "answer": "11.778",
      "points": 15
    },
    {
      "id": 76,
      "wave": 2,
      "question": "$8 - \\frac{5}{8}$",
      "choices": ["5.93", "6.63", "7.375", "9.68"],
      "answer": "7.375",
      "points": 15
    },
    {
      "id": 77,
      "wave": 2,
      "question": "$10 \\times \\frac{1}{7}$",
      "choices": ["1.429", "-2.85", "3.02", "4.07"],
      "answer": "1.429",
      "points": 15
    },
    {
      "id": 78,
      "wave": 2,
      "question": "$20 \\div \\frac{11}{10}$",
      "choices": ["16.26", "15.74", "18.182", "21.78"],
      "answer": "18.182",
      "points": 15
    },
    {
      "id": 79,
      "wave": 2,
      "question": "$18 \\times 5$",
      "choices": ["89.61", "85.99", "87.84", "9E+1"],
      "answer": "9E+1",
      "points": 15
    },
    {
      "id": 80,
      "wave": 2,
      "question": "$5.06 - \\frac{4}{3}$",
      "choices": ["3.727", "4.15", "5.26", "7.42"],
      "answer": "3.727",
      "points": 15
    },
    {
      "id": 81,
      "wave": 2,
      "question": "$14.04 \\times \\frac{4}{7}$",
      "choices": ["3.19", "4.16", "10.45", "8.023"],
      "answer": "8.023",
      "points": 15
    },
    {
      "id": 82,
      "wave": 2,
      "question": "$\\frac{13}{5} \\div 17$",
      "choices": ["0.153", "-0.22", "-2.65", "-3"],
      "answer": "0.153",
      "points": 15
    },
    {
      "id": 83,
      "wave": 2,
      "question": "$0 + 3.32$",
      "choices": ["2.03", "3.32", "3.55", "2.57"],
      "answer": "3.32",
      "points": 15
    },
    {
      "id": 84,
      "wave": 2,
      "question": "$\\frac{10}{7} + 7$",
      "choices": ["8.429", "4.28", "8.24", "6.81"],
      "answer": "8.429",
      "points": 15
    },
    {
      "id": 85,
      "wave": 2,
      "question": "$3 \\times \\frac{8}{9}$",
      "choices": ["2.667", "6.93", "5.9", "4.43"],
      "answer": "2.667",
      "points": 15
    },
    {
      "id": 86,
      "wave": 2,
      "question": "$15.67 + 16.11$",
      "choices": ["33.72", "35.17", "31.78", "29.31"],
      "answer": "31.78",
      "points": 15
    },
    {
      "id": 87,
      "wave": 2,
      "question": "$2.16 \\div 7$",
      "choices": ["-1.69", "0.309", "-2.22", "3.38"],
      "answer": "0.309",
      "points": 15
    },
    {
      "id": 88,
      "wave": 2,
      "question": "$\\frac{5}{2} + 1.04$",
      "choices": ["3.54", "3.79", "4.21", "7.94"],
      "answer": "3.54",
      "points": 15
    },
    {
      "id": 89,
      "wave": 2,
      "question": "$10.11 \\times 2$",
      "choices": ["20.22", "17.43", "22.74", "18.05"],
      "answer": "20.22",
      "points": 15
    },
    {
      "id": 90,
      "wave": 2,
      "question": "$16 + 2$",
      "choices": ["21.65", "18", "22.26", "13.28"],
      "answer": "18",
      "points": 15
    },
    {
      "id": 91,
      "wave": 2,
      "question": "$\\frac{3}{10} \\times 8$",
      "choices": ["0.72", "2.4", "6.98", "-0.42"],
      "answer": "2.4",
      "points": 15
    },
    {
      "id": 92,
      "wave": 2,
      "question": "$3.19 \\times 13.69$",
      "choices": ["43.671", "42.87", "44.13", "44.1"],
      "answer": "43.671",
      "points": 15
    },
    {
      "id": 93,
      "wave": 2,
      "question": "$15.11 \\div 3.38$",
      "choices": ["6.99", "3.85", "9.3", "4.47"],
      "answer": "4.47",
      "points": 15
    },
    {
      "id": 94,
      "wave": 2,
      "question": "$13.13 + 14.72$",
      "choices": ["27.85", "30.02", "28.97", "28.55"],
      "answer": "27.85",
      "points": 15
    },
    {
      "id": 95,
      "wave": 2,
      "question": "$5 - 13.51$",
      "choices": ["-8.51", "-5.46", "-9.47", "-4.74"],
      "answer": "-8.51",
      "points": 15
    },
    {
      "id": 96,
      "wave": 2,
      "question": "$6.92 - 16.41$",
      "choices": ["-13.98", "-9.49", "-7.44", "-11.78"],
      "answer": "-9.49",
      "points": 15
    },
    {
      "id": 97,
      "wave": 2,
      "question": "$10.31 \\div 16.21$",
      "choices": ["0.636", "4.14", "-3.39", "-3.41"],
      "answer": "0.636",
      "points": 15
    },
    {
      "id": 98,
      "wave": 2,
      "question": "$\\frac{1}{6} \\div 10$",
      "choices": ["-0.84", "0.017", "-4", "-2.84"],
      "answer": "0.017",
      "points": 15
    },
    {
      "id": 99,
      "wave": 2,
      "question": "$20 + \\frac{4}{7}$",
      "choices": ["22.95", "21.58", "20.571", "15.78"],
      "answer": "20.571",
      "points": 15
    },
    {
      "id": 100,
      "wave": 2,
      "question": "$\\frac{1}{2} + 2$",
      "choices": ["2.5", "3.76", "1.59", "1.89"],
      "answer": "2.5",
      "points": 15
    },
    {
      "id": 101,
      "wave": 3,
      "question": "$9 \\times 14.37 \\div 11$",
      "choices": ["15.09", "11.757", "11.89", "14.91"],
      "answer": "11.757",
      "points": 20
    },
    {
      "id": 102,
      "wave": 3,
      "question": "$4 \\div \\frac{10}{7} - \\frac{12}{7}$",
      "choices": ["5.41", "-2.26", "5.91", "1.086"],
      "answer": "1.086",
      "points": 20
    },
    {
      "id": 103,
      "wave": 3,
      "question": "$4 \\times 10 - 14.49$",
      "choices": ["28.09", "20.91", "25.51", "21.16"],
      "answer": "25.51",
      "points": 20
    },
    {
      "id": 104,
      "wave": 3,
      "question": "$2.75 \\times \\frac{2}{9} \\times 3.3$",
      "choices": ["3.36", "2.017", "-2.8", "-0.22"],
      "answer": "2.017",
      "points": 20
    },
    {
      "id": 105,
      "wave": 3,
      "question": "$13.15 + \\frac{2}{3} + 10.34$",
      "choices": ["21.02", "23", "20.59", "24.157"],
      "answer": "24.157",
      "points": 20
    },
    {
      "id": 106,
      "wave": 3,
      "question": "$15 + 3.78 \\times 14.4$",
      "choices": ["67.83", "69.432", "68.92", "72.89"],
      "answer": "69.432",
      "points": 20
    },
    {
      "id": 107,
      "wave": 3,
      "question": "$\\frac{7}{9} \\div 7 \\times 4.76$",
      "choices": ["3.27", "2.47", "-1.4", "0.529"],
      "answer": "0.529",
      "points": 20
    },
    {
      "id": 108,
      "wave": 3,
      "question": "$\\frac{1}{10} \\times 3 \\div 7$",
      "choices": ["0.043", "-3.62", "-2.16", "2.93"],
      "answer": "0.043",
      "points": 20
    },
    {
      "id": 109,
      "wave": 3,
      "question": "$10 + 6 \\div 12$",
      "choices": ["9.73", "10.5", "8.18", "12.66"],
      "answer": "10.5",
      "points": 20
    },
    {
      "id": 110,
      "wave": 3,
      "question": "$1 \\times \\frac{1}{3} - 11$",
      "choices": ["-6.19", "-13.35", "-10.667", "-14.87"],
      "answer": "-10.667",
      "points": 20
    },
    {
      "id": 111,
      "wave": 3,
      "question": "$13 \\times 9 + \\frac{9}{7}$",
      "choices": ["118.286", "117.6", "117.57", "113.61"],
      "answer": "118.286",
      "points": 20
    },
    {
      "id": 112,
      "wave": 3,
      "question": "$\\frac{1}{3} + 2.35 + 8$",
      "choices": ["10.683", "12.48", "10.93", "6.35"],
      "answer": "10.683",
      "points": 20
    },
    {
      "id": 113,
      "wave": 3,
      "question": "$12.26 - 8 \\div \\frac{4}{3}$",
      "choices": ["7.66", "2.26", "6.26", "6.09"],
      "answer": "6.26",
      "points": 20
    },
    {
      "id": 114,
      "wave": 3,
      "question": "$4 \\div 12.51 \\times \\frac{1}{7}$",
      "choices": ["0.046", "-2.81", "-2.43", "4.47"],
      "answer": "0.046",
      "points": 20
    },
    {
      "id": 115,
      "wave": 3,
      "question": "$\\frac{1}{10} \\times \\frac{3}{2} - 13.6$",
      "choices": ["-14.85", "-12.04", "-13.45", "-18.3"],
      "answer": "-13.45",
      "points": 20
    },
    {
      "id": 116,
      "wave": 3,
      "question": "$7.1 + \\frac{11}{10} \\div 10$",
      "choices": ["3.42", "7.21", "6.42", "2.49"],
      "answer": "7.21",
      "points": 20
    },
    {
      "id": 117,
      "wave": 3,
      "question": "$15 - 11 \\times 1$",
      "choices": ["7.5", "2.28", "4", "5.28"],
      "answer": "4",
      "points": 20
    },
    {
      "id": 118,
      "wave": 3,
      "question": "$8.56 \\div \\frac{2}{3} \\times 13.81$",
      "choices": ["182.05", "175.89", "177.32", "176.28"],
      "answer": "177.32",
      "points": 20
    },
    {
      "id": 119,
      "wave": 3,
      "question": "$\\frac{7}{10} \\div 14 + \\frac{1}{2}$",
      "choices": ["2.52", "-1.52", "0.55", "3.24"],
      "answer": "0.55",
      "points": 20
    },
    {
      "id": 120,
      "wave": 3,
      "question": "$5 - 1 + 6$",
      "choices": ["1E+1", "7.71", "6.61", "11.15"],
      "answer": "1E+1",
      "points": 20
    },
    {
      "id": 121,
      "wave": 3,
      "question": "$7.23 \\div \\frac{9}{10} \\times 5$",
      "choices": ["40.167", "37.64", "43.6", "40.74"],
      "answer": "40.167",
      "points": 20
    },
    {
      "id": 122,
      "wave": 3,
      "question": "$9.54 - 3.22 - 14.8$",
      "choices": ["-12.18", "-7.42", "-8.48", "-4.79"],
      "answer": "-8.48",
      "points": 20
    },
    {
      "id": 123,
      "wave": 3,
      "question": "$\\frac{3}{8} - \\frac{14}{9} \\div 3$",
      "choices": ["-2.85", "-4.26", "-0.144", "3.57"],
      "answer": "-0.144",
      "points": 20
    },
    {
      "id": 124,
      "wave": 3,
      "question": "$10.61 \\div 10 - \\frac{1}{3}$",
      "choices": ["0.728", "1.67", "-2.37", "-4.11"],
      "answer": "0.728",
      "points": 20
    },
    {
      "id": 125,
      "wave": 3,
      "question": "$13.21 \\times 5.2 - 8$",
      "choices": ["64.15", "62.61", "59.26", "60.692"],
      "answer": "60.692",
      "points": 20
    },
    {
      "id": 126,
      "wave": 3,
      "question": "$14 \\div \\frac{1}{4} - \\frac{14}{3}$",
      "choices": ["53.06", "49.97", "51.333", "48.13"],
      "answer": "51.333",
      "points": 20
    },
    {
      "id": 127,
      "wave": 3,
      "question": "$\\frac{7}{8} - \\frac{2}{9} \\times 6.19$",
      "choices": ["-4.88", "-0.501", "1.02", "0.72"],
      "answer": "-0.501",
      "points": 20
    },
    {
      "id": 128,
      "wave": 3,
      "question": "$\\frac{4}{7} \\div 12 + 13$",
      "choices": ["13.048", "14.92", "17.37", "9.16"],
      "answer": "13.048",
      "points": 20
    },
    {
      "id": 129,
      "wave": 3,
      "question": "$1 \\div 2 + \\frac{1}{4}$",
      "choices": ["4.69", "0.75", "1.06", "-4.17"],
      "answer": "0.75",
      "points": 20
    },
    {
      "id": 130,
      "wave": 3,
      "question": "$6 \\times 9.45 \\div 11$",
      "choices": ["2.36", "3.73", "5.43", "5.155"],
      "answer": "5.155",
      "points": 20
    },
    {
      "id": 131,
      "wave": 3,
      "question": "$1 - 1 \\div 4$",
      "choices": ["0.75", "4.93", "-3.28", "-0.38"],
      "answer": "0.75",
      "points": 20
    },
    {
      "id": 132,
      "wave": 3,
      "question": "$\\frac{4}{7} + \\frac{9}{10} \\times \\frac{9}{10}$",
      "choices": ["-0.2", "1.381", "-0.3", "3.73"],
      "answer": "1.381",
      "points": 20
    },
    {
      "id": 133,
      "wave": 3,
      "question": "$\\frac{7}{4} - 11 + \\frac{1}{6}$",
      "choices": ["-4.78", "-9.083", "-4.1", "-7.19"],
      "answer": "-9.083",
      "points": 20
    },
    {
      "id": 134,
      "wave": 3,
      "question": "$10.9 \\times 8 + \\frac{15}{2}$",
      "choices": ["92.1", "95.61", "91.93", "94.7"],
      "answer": "94.7",
      "points": 20
    },
    {
      "id": 135,
      "wave": 3,
      "question": "$2 + 8.6 + 5$",
      "choices": ["20.23", "18.64", "15.6", "19.14"],
      "answer": "15.6",
      "points": 20
    },
    {
      "id": 136,
      "wave": 3,
      "question": "$5.7 \\times 5 - 5$",
      "choices": ["25.62", "22.09", "23.5", "22.28"],
      "answer": "23.5",
      "points": 20
    },
    {
      "id": 137,
      "wave": 3,
      "question": "$\\frac{5}{3} - 1 + \\frac{2}{9}$",
      "choices": ["0.889", "4.83", "5.5", "-0.46"],
      "answer": "0.889",
      "points": 20
    },
    {
      "id": 138,
      "wave": 3,
      "question": "$1.59 \\times 4.03 \\div 1.17$",
      "choices": ["5.477", "4.09", "4.15", "5.29"],
      "answer": "5.477",
      "points": 20
    },
    {
      "id": 139,
      "wave": 3,
      "question": "$\\frac{2}{3} - 7 + 3$",
      "choices": ["-1.8", "-3.333", "-0.17", "0.53"],
      "answer": "-3.333",
      "points": 20
    },
    {
      "id": 140,
      "wave": 3,
      "question": "$\\frac{1}{9} \\div \\frac{4}{9} + 7.66$",
      "choices": ["7.63", "9.19", "6.59", "7.91"],
      "answer": "7.91",
      "points": 20
    },
    {
      "id": 141,
      "wave": 3,
      "question": "$10 - \\frac{5}{6} \\div \\frac{1}{5}$",
      "choices": ["5.7", "7.83", "3.72", "5.833"],
      "answer": "5.833",
      "points": 20
    },
    {
      "id": 142,
      "wave": 3,
      "question": "$8.71 - \\frac{3}{7} - 5$",
      "choices": ["4.51", "3.281", "1.5", "5.39"],
      "answer": "3.281",
      "points": 20
    },
    {
      "id": 143,
      "wave": 3,
      "question": "$7 - 2 - \\frac{11}{10}$",
      "choices": ["0.15", "8.54", "1.72", "3.9"],
      "answer": "3.9",
      "points": 20
    },
    {
      "id": 144,
      "wave": 3,
      "question": "$1 \\div 6 \\div 7.58$",
      "choices": ["3.73", "-1.93", "-3.02", "0.022"],
      "answer": "0.022",
      "points": 20
    },
    {
      "id": 145,
      "wave": 3,
      "question": "$13.46 + 14.68 + 5.06$",
      "choices": ["33.2", "34.61", "31.07", "32.85"],
      "answer": "33.2",
      "points": 20
    },
    {
      "id": 146,
      "wave": 3,
      "question": "$\\frac{4}{5} \\div 2.22 - 8$",
      "choices": ["-10.79", "-6.38", "-7.64", "-12.51"],
      "answer": "-7.64",
      "points": 20
    },
    {
      "id": 147,
      "wave": 3,
      "question": "$\\frac{1}{7} \\times \\frac{2}{3} \\div 2$",
      "choices": ["-1.05", "0.88", "-3.78", "0.048"],
      "answer": "0.048",
      "points": 20
    },
    {
      "id": 148,
      "wave": 3,
      "question": "$12 \\div 10.14 \\times 5$",
      "choices": ["5.2", "8.31", "5.917", "3.91"],
      "answer": "5.917",
      "points": 20
    },
    {
      "id": 149,
      "wave": 3,
      "question": "$\\frac{3}{2} + 13.06 - 12$",
      "choices": ["4.48", "3.78", "2.56", "-0.4"],
      "answer": "2.56",
      "points": 20
    },
    {
      "id": 150,
      "wave": 3,
      "question": "$13.22 - \\frac{4}{9} - 5.19$",
      "choices": ["7.586", "9.31", "6.41", "7.77"],
      "answer": "7.586",
      "points": 20
    },
    {
      "id": 151,
      "wave": 4,
      "question": "$5 - 6 - ( 7 \\times 18.77 )$",
      "choices": ["-132.39", "-130.61", "-128.47", "-128.73"],
      "answer": "-132.39",
      "points": 25
    },
    {
      "id": 152,
      "wave": 4,
      "question": "$( 17.16 \\div 7.03 ) \\times 6.47 \\div 16$",
      "choices": ["0.43", "-2.49", "-1.05", "0.987"],
      "answer": "0.987",
      "points": 25
    },
    {
      "id": 153,
      "wave": 4,
      "question": "$6 \\div \\frac{1}{7} + 13.66 \\div \\frac{13}{3}$",
      "choices": ["46.82", "45.152", "48.45", "42.44"],
      "answer": "45.152",
      "points": 25
    },
    {
      "id": 154,
      "wave": 4,
      "question": "$24.19 - ( \\frac{1}{5} \\times \\frac{7}{4} )$",
      "choices": ["23.34", "23.84", "21.49", "23.59"],
      "answer": "23.84",
      "points": 25
    },
    {
      "id": 155,
      "wave": 4,
      "question": "$4.41 + ( 21 - 6.98 )$",
      "choices": ["16.79", "21.35", "18.43", "15.37"],
      "answer": "18.43",
      "points": 25
    },
    {
      "id": 156,
      "wave": 4,
      "question": "$( 15.52 \\times \\frac{1}{7} ) \\div \\frac{13}{9}$",
      "choices": ["6.28", "1.535", "-0.12", "3.86"],
      "answer": "1.535",
      "points": 25
    },
    {
      "id": 157,
      "wave": 4,
      "question": "$( \\frac{3}{10} \\times 3 ) + \\frac{1}{2} \\div \\frac{5}{9}$",
      "choices": ["6.34", "5.48", "5.43", "1.8"],
      "answer": "1.8",
      "points": 25
    },
    {
      "id": 158,
      "wave": 4,
      "question": "$14.58 - ( 5.67 \\div 3 ) + 20$",
      "choices": ["32.69", "29.28", "29.87", "33.11"],
      "answer": "32.69",
      "points": 25
    },
    {
      "id": 159,
      "wave": 4,
      "question": "$5 - 3 \\times 3.46 + 15$",
      "choices": ["6.31", "8.61", "9.62", "6.19"],
      "answer": "9.62",
      "points": 25
    },
    {
      "id": 160,
      "wave": 4,
      "question": "$( \\frac{14}{9} \\times 3.71 ) + 16$",
      "choices": ["18.8", "20.32", "18.22", "21.771"],
      "answer": "21.771",
      "points": 25
    },
    {
      "id": 161,
      "wave": 4,
      "question": "$9 \\times \\frac{9}{8} \\div 3 + 8.02$",
      "choices": ["11.395", "14.74", "7.88", "11.68"],
      "answer": "11.395",
      "points": 25
    },
    {
      "id": 162,
      "wave": 4,
      "question": "$( 13.12 \\div \\frac{15}{8} ) - \\frac{6}{5}$",
      "choices": ["6.77", "9.67", "9.79", "5.797"],
      "answer": "5.797",
      "points": 25
    },
    {
      "id": 163,
      "wave": 4,
      "question": "$17 + 6 \\times 9.54 \\div 2.69$",
      "choices": ["36.75", "40.62", "33.47", "38.279"],
      "answer": "38.279",
      "points": 25
    },
    {
      "id": 164,
      "wave": 4,
      "question": "$21 - ( 22 - 25 )$",
      "choices": ["26.32", "20.03", "27.82", "24"],
      "answer": "24",
      "points": 25
    },
    {
      "id": 165,
      "wave": 4,
      "question": "$( \\frac{8}{5} \\times 4 ) + \\frac{7}{5}$",
      "choices": ["7.57", "7.8", "9.43", "4.43"],
      "answer": "7.8",
      "points": 25
    },
    {
      "id": 166,
      "wave": 4,
      "question": "$19.72 - \\frac{7}{10} \\div 16.23 \\times \\frac{2}{5}$",
      "choices": ["19.19", "16.49", "24.02", "19.703"],
      "answer": "19.703",
      "points": 25
    },
    {
      "id": 167,
      "wave": 4,
      "question": "$13.06 - 8.8 \\div 18 - 21$",
      "choices": ["-10.17", "-8.429", "-8.62", "-6.36"],
      "answer": "-8.429",
      "points": 25
    },
    {
      "id": 168,
      "wave": 4,
      "question": "$4 + ( \\frac{8}{9} \\div 22.32 )$",
      "choices": ["5.34", "6.52", "-0.58", "4.04"],
      "answer": "4.04",
      "points": 25
    },
    {
      "id": 169,
      "wave": 4,
      "question": "$3.67 \\times 1 + \\frac{5}{6}$",
      "choices": ["5.4", "5.65", "4.503", "6.14"],
      "answer": "4.503",
      "points": 25
    },
    {
      "id": 170,
      "wave": 4,
      "question": "$11 \\div 13 + \\frac{9}{10}$",
      "choices": ["1.746", "-2.7", "1.46", "-1.67"],
      "answer": "1.746",
      "points": 25
    },
    {
      "id": 171,
      "wave": 4,
      "question": "$17 \\div \\frac{13}{7} + 17.36 \\div 24$",
      "choices": ["9.877", "9.3", "10.48", "5.34"],
      "answer": "9.877",
      "points": 25
    },
    {
      "id": 172,
      "wave": 4,
      "question": "$5 \\div \\frac{1}{4} \\div 24$",
      "choices": ["-0.42", "4.6", "-0", "0.833"],
      "answer": "0.833",
      "points": 25
    },
    {
      "id": 173,
      "wave": 4,
      "question": "$16.79 + \\frac{9}{10} \\times 10.85 \\div \\frac{1}{5}$",
      "choices": ["64.01", "68.96", "65.615", "64.84"],
      "answer": "65.615",
      "points": 25
    },
    {
      "id": 174,
      "wave": 4,
      "question": "$11 + 23.05 - ( \\frac{5}{8} \\times 1 )$",
      "choices": ["36.8", "34.58", "33.425", "37.01"],
      "answer": "33.425",
      "points": 25
    },
    {
      "id": 175,
      "wave": 4,
      "question": "$20 + \\frac{5}{4} + ( 17 \\div 2.4 )$",
      "choices": ["31.23", "28.98", "28.333", "28.64"],
      "answer": "28.333",
      "points": 25
    },
    {
      "id": 176,
      "wave": 4,
      "question": "$21 \\div 14.82 - 12$",
      "choices": ["-7.31", "-13.24", "-12.78", "-10.583"],
      "answer": "-10.583",
      "points": 25
    },
    {
      "id": 177,
      "wave": 4,
      "question": "$23 - 20.07 \\times 23.88$",
      "choices": ["-456.13", "-456.272", "-458.78", "-451.38"],
      "answer": "-456.272",
      "points": 25
    },
    {
      "id": 178,
      "wave": 4,
      "question": "$19.96 \\div 18.76 \\times \\frac{5}{9} \\times 2$",
      "choices": ["2.86", "1.182", "6.08", "0.09"],
      "answer": "1.182",
      "points": 25
    },
    {
      "id": 179,
      "wave": 4,
      "question": "$\\frac{4}{9} \\times 17 + \\frac{11}{3} + \\frac{8}{5}$",
      "choices": ["11.34", "11.65", "12.822", "15.09"],
      "answer": "12.822",
      "points": 25
    },
    {
      "id": 180,
      "wave": 4,
      "question": "$( \\frac{7}{6} - 21.9 ) - 6.74$",
      "choices": ["-27.473", "-24.63", "-27.83", "-28.02"],
      "answer": "-27.473",
      "points": 25
    },
    {
      "id": 181,
      "wave": 4,
      "question": "$( 22.1 \\times \\frac{5}{4} ) - \\frac{3}{5}$",
      "choices": ["30.52", "23.6", "31.07", "27.025"],
      "answer": "27.025",
      "points": 25
    },
    {
      "id": 182,
      "wave": 4,
      "question": "$\\frac{3}{2} - \\frac{7}{4} - \\frac{5}{7} \\div 3.28$",
      "choices": ["-4.8", "0.55", "-0.468", "-1.68"],
      "answer": "-0.468",
      "points": 25
    },
    {
      "id": 183,
      "wave": 4,
      "question": "$\\frac{5}{9} \\times 16 \\div 21.01 - 18.19$",
      "choices": ["-21.2", "-22.56", "-19.97", "-17.767"],
      "answer": "-17.767",
      "points": 25
    },
    {
      "id": 184,
      "wave": 4,
      "question": "$2.28 - ( \\frac{8}{9} \\div \\frac{1}{7} )$",
      "choices": ["-3.942", "-2.51", "-3.12", "-7.47"],
      "answer": "-3.942",
      "points": 25
    },
    {
      "id": 185,
      "wave": 4,
      "question": "$( 18 \\times 19.25 ) + \\frac{1}{10} \\times \\frac{1}{2}$",
      "choices": ["346.55", "349.2", "342.14", "350.95"],
      "answer": "346.55",
      "points": 25
    },
    {
      "id": 186,
      "wave": 4,
      "question": "$\\frac{19}{8} + \\frac{1}{3} - ( \\frac{11}{10} \\times 11.62 )$",
      "choices": ["-7.39", "-6.38", "-10.074", "-13.83"],
      "answer": "-10.074",
      "points": 25
    },
    {
      "id": 187,
      "wave": 4,
      "question": "$12.27 \\div 4 - 7.78 \\div 20.54$",
      "choices": ["4.48", "4.41", "-0.53", "2.689"],
      "answer": "2.689",
      "points": 25
    },
    {
      "id": 188,
      "wave": 4,
      "question": "$16.86 \\div \\frac{1}{2} \\div 6$",
      "choices": ["5.62", "6.08", "9.62", "9.34"],
      "answer": "5.62",
      "points": 25
    },
    {
      "id": 189,
      "wave": 4,
      "question": "$\\frac{1}{4} \\div \\frac{5}{7} + 3.89 + 8.9$",
      "choices": ["12.16", "10.58", "14.6", "13.14"],
      "answer": "13.14",
      "points": 25
    },
    {
      "id": 190,
      "wave": 4,
      "question": "$\\frac{2}{7} \\div 6 \\div 5$",
      "choices": ["3.81", "0.01", "4.08", "-3.73"],
      "answer": "0.01",
      "points": 25
    },
    {
      "id": 191,
      "wave": 4,
      "question": "$\\frac{5}{9} + \\frac{21}{10} + \\frac{1}{10}$",
      "choices": ["2.756", "7.42", "3.58", "1.24"],
      "answer": "2.756",
      "points": 25
    },
    {
      "id": 192,
      "wave": 4,
      "question": "$\\frac{3}{8} \\times \\frac{1}{10} \\times \\frac{7}{5} - 10.26$",
      "choices": ["-11.79", "-13.61", "-10.208", "-9.71"],
      "answer": "-10.208",
      "points": 25
    },
    {
      "id": 193,
      "wave": 4,
      "question": "$\\frac{5}{6} \\times 2.8 + 9.11$",
      "choices": ["10.66", "11.9", "11.443", "13.18"],
      "answer": "11.443",
      "points": 25
    },
    {
      "id": 194,
      "wave": 4,
      "question": "$23 \\times 14 - ( 1 \\times \\frac{11}{6} )$",
      "choices": ["320.167", "318.46", "325.11", "315.42"],
      "answer": "320.167",
      "points": 25
    },
    {
      "id": 195,
      "wave": 4,
      "question": "$22 \\div ( 7 \\div \\frac{5}{3} )$",
      "choices": ["9.46", "5.238", "8.22", "4.13"],
      "answer": "5.238",
      "points": 25
    },
    {
      "id": 196,
      "wave": 4,
      "question": "$18 + 3.6 - ( 21 \\div \\frac{25}{6} )$",
      "choices": ["19.82", "12.95", "16.56", "21.23"],
      "answer": "16.56",
      "points": 25
    },
    {
      "id": 197,
      "wave": 4,
      "question": "$( \\frac{25}{4} \\div 5.15 ) - 13$",
      "choices": ["-9.02", "-11.786", "-15.04", "-15.17"],
      "answer": "-11.786",
      "points": 25
    },
    {
      "id": 198,
      "wave": 4,
      "question": "$17.4 \\div \\frac{1}{3} + ( 17 \\times \\frac{13}{6} )$",
      "choices": ["89.033", "86.4", "84.27", "92.81"],
      "answer": "89.033",
      "points": 25
    },
    {
      "id": 199,
      "wave": 4,
      "question": "$\\frac{1}{10} - 5.75 + ( \\frac{1}{2} \\times \\frac{1}{10} )$",
      "choices": ["-5.05", "-5.6", "-8.45", "-4.29"],
      "answer": "-5.6",
      "points": 25
    },
    {
      "id": 200,
      "wave": 4,
      "question": "$\\frac{4}{7} - ( 10 + 6.39 )$",
      "choices": ["-13.2", "-15.819", "-17.56", "-16.94"],
      "answer": "-15.819",
      "points": 25
    },
    {
      "id": 201,
      "wave": 5,
      "question": "$( \\frac{21}{10} \\div \\frac{20}{9} ) - \\frac{4}{5}$",
      "choices": ["0.145", "-0.33", "3.95", "-4.14"],
      "answer": "0.145",
      "points": 30
    },
    {
      "id": 202,
      "wave": 5,
      "question": "$\\frac{9}{8} - 31.4 \\div ( 8.45 \\times 27.65 )$",
      "choices": ["4.6", "0.991", "-1.89", "-2.8"],
      "answer": "0.991",
      "points": 30
    },
    {
      "id": 203,
      "wave": 5,
      "question": "$35.94 - 24 + 34 - 24$",
      "choices": ["22.73", "18.61", "21.94", "25.3"],
      "answer": "21.94",
      "points": 30
    },
    {
      "id": 204,
      "wave": 5,
      "question": "$15 - 5 \\div 18.92$",
      "choices": ["16.45", "14.736", "9.94", "17.94"],
      "answer": "14.736",
      "points": 30
    },
    {
      "id": 205,
      "wave": 5,
      "question": "$40 + 30.74 \\div 37.12$",
      "choices": ["40.828", "45.63", "36.52", "42.33"],
      "answer": "40.828",
      "points": 30
    },
    {
      "id": 206,
      "wave": 5,
      "question": "$( 23.64 \\div \\frac{1}{9} ) + \\frac{6}{7} \\div 17.34$",
      "choices": ["211.34", "214.2", "212.809", "208.05"],
      "answer": "212.809",
      "points": 30
    },
    {
      "id": 207,
      "wave": 5,
      "question": "$26.89 \\div 39.88 \\times 28.84$",
      "choices": ["17.86", "15.14", "18.89", "19.446"],
      "answer": "19.446",
      "points": 30
    },
    {
      "id": 208,
      "wave": 5,
      "question": "$\\frac{1}{3} + ( 31.36 - \\frac{9}{4} ) - \\frac{27}{10}$",
      "choices": ["24.33", "23.87", "26.3", "26.743"],
      "answer": "26.743",
      "points": 30
    },
    {
      "id": 209,
      "wave": 5,
      "question": "$( \\frac{29}{7} \\div 27.37 ) + 23 - 9.87$",
      "choices": ["13.281", "12.69", "14.65", "8.43"],
      "answer": "13.281",
      "points": 30
    },
    {
      "id": 210,
      "wave": 5,
      "question": "$\\frac{11}{10} + \\frac{11}{8} \\times \\frac{4}{7}$",
      "choices": ["-2.5", "1.886", "-3.09", "4.81"],
      "answer": "1.886",
      "points": 30
    },
    {
      "id": 211,
      "wave": 5,
      "question": "$\\frac{2}{9} + \\frac{1}{2} + 19 \\div \\frac{4}{9}$",
      "choices": ["45.87", "43.83", "43.472", "40.32"],
      "answer": "43.472",
      "points": 30
    },
    {
      "id": 212,
      "wave": 5,
      "question": "$\\frac{37}{7} - 30 - 29 + 13.32$",
      "choices": ["-40.394", "-45.19", "-37.63", "-40.28"],
      "answer": "-40.394",
      "points": 30
    },
    {
      "id": 213,
      "wave": 5,
      "question": "$33.63 \\times ( \\frac{11}{10} \\div 20.92 ) - \\frac{5}{7}$",
      "choices": ["1.054", "-3.94", "3.77", "3.86"],
      "answer": "1.054",
      "points": 30
    },
    {
      "id": 214,
      "wave": 5,
      "question": "$( 38.21 \\times 21.09 ) \\div 35 + 9$",
      "choices": ["31.05", "30.12", "32.024", "32.98"],
      "answer": "32.024",
      "points": 30
    },
    {
      "id": 215,
      "wave": 5,
      "question": "$\\frac{1}{3} + 7.74 \\times \\frac{11}{10} \\div 33$",
      "choices": ["-2.12", "0.591", "-3.4", "-2.78"],
      "answer": "0.591",
      "points": 30
    },
    {
      "id": 216,
      "wave": 5,
      "question": "$5 \\div 38 + 38$",
      "choices": ["36.01", "37.43", "36.8", "38.132"],
      "answer": "38.132",
      "points": 30
    },
    {
      "id": 217,
      "wave": 5,
      "question": "$( \\frac{40}{7} \\div 12.28 ) - 19.35 \\div \\frac{13}{9}$",
      "choices": ["-10.19", "-12.931", "-11.44", "-15.46"],
      "answer": "-12.931",
      "points": 30
    },
    {
      "id": 218,
      "wave": 5,
      "question": "$( 33 + 13.7 ) + 10 - \\frac{4}{3}$",
      "choices": ["54.61", "52.07", "55.367", "57.2"],
      "answer": "55.367",
      "points": 30
    },
    {
      "id": 219,
      "wave": 5,
      "question": "$18.4 \\div 14.77 + \\frac{4}{3} \\div 1$",
      "choices": ["-0.34", "-1.17", "2.579", "1.61"],
      "answer": "2.579",
      "points": 30
    },
    {
      "id": 220,
      "wave": 5,
      "question": "$17.14 + ( \\frac{8}{3} - 8.14 )$",
      "choices": ["15.03", "11.667", "12.35", "14.82"],
      "answer": "11.667",
      "points": 30
    },
    {
      "id": 221,
      "wave": 5,
      "question": "$37.05 \\div 27.05 \\times \\frac{37}{7}$",
      "choices": ["6.02", "7.12", "11.89", "7.24"],
      "answer": "7.24",
      "points": 30
    },
    {
      "id": 222,
      "wave": 5,
      "question": "$7 \\div ( 25.45 \\times 16 ) \\times \\frac{4}{9}$",
      "choices": ["0.008", "4.84", "-1.47", "0.33"],
      "answer": "0.008",
      "points": 30
    },
    {
      "id": 223,
      "wave": 5,
      "question": "$( 15.49 \\div 37 ) + 37$",
      "choices": ["41.2", "37.419", "35.66", "41.68"],
      "answer": "37.419",
      "points": 30
    },
    {
      "id": 224,
      "wave": 5,
      "question": "$\\frac{5}{2} + 16.4 - ( 29.01 \\div \\frac{20}{9} )$",
      "choices": ["8.16", "2.17", "1.65", "5.846"],
      "answer": "5.846",
      "points": 30
    },
    {
      "id": 225,
      "wave": 5,
      "question": "$14 \\div 27.45 - \\frac{20}{7}$",
      "choices": ["-2.347", "-5.13", "-2.77", "-6.49"],
      "answer": "-2.347",
      "points": 30
    },
    {
      "id": 226,
      "wave": 5,
      "question": "$21 + ( 28.45 \\times \\frac{1}{6} ) \\div 12.78$",
      "choices": ["21.371", "19.24", "16.48", "20.67"],
      "answer": "21.371",
      "points": 30
    },
    {
      "id": 227,
      "wave": 5,
      "question": "$21 - 10.67 + 29 \\div 37$",
      "choices": ["10.11", "7.12", "15.35", "11.114"],
      "answer": "11.114",
      "points": 30
    },
    {
      "id": 228,
      "wave": 5,
      "question": "$27 - 30.53 + ( 39 - \\frac{6}{7} )$",
      "choices": ["30.91", "34.613", "34.3", "39.31"],
      "answer": "34.613",
      "points": 30
    },
    {
      "id": 229,
      "wave": 5,
      "question": "$\\frac{1}{8} + 32.62 + 36$",
      "choices": ["68.29", "72.24", "68.745", "72.77"],
      "answer": "68.745",
      "points": 30
    },
    {
      "id": 230,
      "wave": 5,
      "question": "$40 \\div 9.1 \\times ( 38.25 \\div \\frac{4}{9} )$",
      "choices": ["378.65", "378.297", "373.73", "373.56"],
      "answer": "378.297",
      "points": 30
    },
    {
      "id": 231,
      "wave": 5,
      "question": "$24 \\div 10.62 + 19 - 8$",
      "choices": ["10.91", "13.26", "16.42", "16.48"],
      "answer": "13.26",
      "points": 30
    },
    {
      "id": 232,
      "wave": 5,
      "question": "$40 \\div \\frac{5}{4} - \\frac{29}{8}$",
      "choices": ["28.48", "23.71", "23.54", "28.375"],
      "answer": "28.375",
      "points": 30
    },
    {
      "id": 233,
      "wave": 5,
      "question": "$11 \\times 22.21 \\times 29.47 \\div 21$",
      "choices": ["347.05", "340.15", "339.66", "342.848"],
      "answer": "342.848",
      "points": 30
    },
    {
      "id": 234,
      "wave": 5,
      "question": "$40 \\div 39.56 + 36 - \\frac{22}{9}$",
      "choices": ["30.34", "34.73", "34.567", "34.24"],
      "answer": "34.567",
      "points": 30
    },
    {
      "id": 235,
      "wave": 5,
      "question": "$( \\frac{9}{10} \\times 7.84 ) + \\frac{1}{2} \\div \\frac{17}{6}$",
      "choices": ["2.56", "11.66", "10.38", "7.232"],
      "answer": "7.232",
      "points": 30
    },
    {
      "id": 236,
      "wave": 5,
      "question": "$( \\frac{1}{2} \\times 37.46 ) + 30.07 + \\frac{29}{9}$",
      "choices": ["56.26", "50.26", "47.49", "52.022"],
      "answer": "52.022",
      "points": 30
    },
    {
      "id": 237,
      "wave": 5,
      "question": "$\\frac{11}{9} + ( \\frac{13}{9} + 32.49 )$",
      "choices": ["39.11", "30.93", "35.157", "34.39"],
      "answer": "35.157",
      "points": 30
    },
    {
      "id": 238,
      "wave": 5,
      "question": "$\\frac{21}{8} + 14 \\div 26.75$",
      "choices": ["1.18", "-0.83", "3.148", "3.01"],
      "answer": "3.148",
      "points": 30
    },
    {
      "id": 239,
      "wave": 5,
      "question": "$38 + 7 \\div 15.47 + 37.66$",
      "choices": ["76.72", "77.01", "76.112", "77.69"],
      "answer": "76.112",
      "points": 30
    },
    {
      "id": 240,
      "wave": 5,
      "question": "$\\frac{1}{4} \\div 24.9 + ( 12.6 \\div \\frac{3}{4} )$",
      "choices": ["14.27", "21.56", "12.55", "16.81"],
      "answer": "16.81",
      "points": 30
    },
    {
      "id": 241,
      "wave": 5,
      "question": "$22.53 \\div \\frac{5}{6} \\div 21.88$",
      "choices": ["2.57", "-3.54", "1.236", "2.43"],
      "answer": "1.236",
      "points": 30
    },
    {
      "id": 242,
      "wave": 5,
      "question": "$26 \\times 30.09 \\div 25.83 - 5$",
      "choices": ["23.52", "25.11", "25.288", "25.16"],
      "answer": "25.288",
      "points": 30
    },
    {
      "id": 243,
      "wave": 5,
      "question": "$33.74 \\times \\frac{2}{3} - \\frac{5}{6} - 18.22$",
      "choices": ["5.82", "2.99", "3.05", "3.44"],
      "answer": "3.44",
      "points": 30
    },
    {
      "id": 244,
      "wave": 5,
      "question": "$5.33 - 31 + 22.75$",
      "choices": ["-1.1", "-2.92", "-6.25", "-7.09"],
      "answer": "-2.92",
      "points": 30
    },
    {
      "id": 245,
      "wave": 5,
      "question": "$\\frac{11}{9} + 7.62 - 11 - 5.47$",
      "choices": ["-6.59", "-3.17", "-10.81", "-7.628"],
      "answer": "-7.628",
      "points": 30
    },
    {
      "id": 246,
      "wave": 5,
      "question": "$8.45 + 1 - 11.37 - \\frac{3}{2}$",
      "choices": ["-1.67", "-0.39", "-3.42", "-0.13"],
      "answer": "-3.42",
      "points": 30
    },
    {
      "id": 247,
      "wave": 5,
      "question": "$\\frac{7}{4} - ( 38 \\div 15.3 ) + 27$",
      "choices": ["26.15", "25.34", "26.266", "26.51"],
      "answer": "26.266",
      "points": 30
    },
    {
      "id": 248,
      "wave": 5,
      "question": "$37 - \\frac{4}{5} \\times \\frac{1}{4}$",
      "choices": ["34.78", "34.86", "41.39", "36.8"],
      "answer": "36.8",
      "points": 30
    },
    {
      "id": 249,
      "wave": 5,
      "question": "$33.07 \\div 34.93 \\div 16.07$",
      "choices": ["-3.03", "0.059", "-2.32", "4.12"],
      "answer": "0.059",
      "points": 30
    },
    {
      "id": 250,
      "wave": 5,
      "question": "$16.27 + ( 31 \\div 26 )$",
      "choices": ["15.31", "13.36", "17.462", "18.81"],
      "answer": "17.462",
      "points": 30
    }
  ]
}
