{
  "title": "Solving Equations by Factoring",
  "description": "Solve linear equations by applying GCF factoring, zero product property, factor by grouping, perfect squares, difference of squares, and quadratic factoring.",
  "waves": 5,
  "timePerQuestion": 180,
  "questions": [
    {
      "id": 1,
      "wave": 1,
      "question": "Solve for $x$: $x(x + 5) = 0$.",
      "choices": ["$x = 0, x = -5$", "$x = 0, x = 5$", "$x = -5$", "$x = 5$"],
      "answer": "$x = 0, x = -5$",
      "points": 10
    },
    {
      "id": 2,
      "wave": 1,
      "question": "Solve for $y$: $(y - 3)(y + 2) = 0$.",
      "choices": ["$y = 3, y = -2$", "$y = -3, y = 2$", "$y = 3$", "$y = -2$"],
      "answer": "$y = 3, y = -2$",
      "points": 10
    },
    {
      "id": 3,
      "wave": 1,
      "question": "Solve for $a$: $a^2 + 7a = 0$.",
      "choices": ["$a = 0, a = -7$", "$a = 0, a = 7$", "$a = -7$", "$a = 7$"],
      "answer": "$a = 0, a = -7$",
      "points": 10
    },
    {
      "id": 4,
      "wave": 1,
      "question": "Solve for $b$: $b^2 - 9 = 0$.",
      "choices": ["$b = 3, b = -3$", "$b = 9$", "$b = -9$", "$b = 0$"],
      "answer": "$b = 3, b = -3$",
      "points": 10
    },
    {
      "id": 5,
      "wave": 1,
      "question": "Solve for $c$: $c^2 + 5c + 6 = 0$.",
      "choices": [
        "$c = -2, c = -3$",
        "$c = 2, c = 3$",
        "$c = -2, c = 3$",
        "$c = 2, c = -3$"
      ],
      "answer": "$c = -2, c = -3$",
      "points": 10
    },
    {
      "id": 6,
      "wave": 1,
      "question": "Solve for $x$: $2x^2 + 4x = 0$.",
      "choices": ["$x = 0, x = -2$", "$x = 0, x = 2$", "$x = -2$", "$x = 2$"],
      "answer": "$x = 0, x = -2$",
      "points": 10
    },
    {
      "id": 7,
      "wave": 1,
      "question": "Solve for $y$: $(y + 4)(y - 1) = 0$.",
      "choices": ["$y = -4, y = 1$", "$y = 4, y = -1$", "$y = -4$", "$y = 1$"],
      "answer": "$y = -4, y = 1$",
      "points": 10
    },
    {
      "id": 8,
      "wave": 1,
      "question": "Solve for $m$: $m^2 - 16 = 0$.",
      "choices": ["$m = 4, m = -4$", "$m = 16$", "$m = -16$", "$m = 0$"],
      "answer": "$m = 4, m = -4$",
      "points": 10
    },
    {
      "id": 9,
      "wave": 1,
      "question": "Solve for $n$: $n^2 - 4n + 3 = 0$.",
      "choices": [
        "$n = 1, n = 3$",
        "$n = -1, n = -3$",
        "$n = 1, n = -3$",
        "$n = -1, n = 3$"
      ],
      "answer": "$n = 1, n = 3$",
      "points": 10
    },
    {
      "id": 10,
      "wave": 1,
      "question": "Solve for $p$: $3p^2 - 9p = 0$.",
      "choices": ["$p = 0, p = 3$", "$p = 0, p = -3$", "$p = 3$", "$p = -3$"],
      "answer": "$p = 0, p = 3$",
      "points": 10
    },
    {
      "id": 11,
      "wave": 1,
      "question": "Solve for $q$: $(q - 7)(q - 2) = 0$.",
      "choices": [
        "$q = 7, q = 2$",
        "$q = -7, q = -2$",
        "$q = 7, q = -2$",
        "$q = -7, q = 2$"
      ],
      "answer": "$q = 7, q = 2$",
      "points": 10
    },
    {
      "id": 12,
      "wave": 1,
      "question": "Solve for $r$: $r^2 - 1 = 0$.",
      "choices": ["$r = 1, r = -1$", "$r = 1$", "$r = -1$", "$r = 0$"],
      "answer": "$r = 1, r = -1$",
      "points": 10
    },
    {
      "id": 13,
      "wave": 1,
      "question": "Solve for $s$: $s^2 + 8s + 15 = 0$.",
      "choices": [
        "$s = -3, s = -5$",
        "$s = 3, s = 5$",
        "$s = -3, s = 5$",
        "$s = 3, s = -5$"
      ],
      "answer": "$s = -3, s = -5$",
      "points": 10
    },
    {
      "id": 14,
      "wave": 1,
      "question": "Solve for $t$: $5t^2 + 10t = 0$.",
      "choices": ["$t = 0, t = -2$", "$t = 0, t = 2$", "$t = -2$", "$t = 2$"],
      "answer": "$t = 0, t = -2$",
      "points": 10
    },
    {
      "id": 15,
      "wave": 1,
      "question": "Solve for $u$: $(u + 6)(u + 1) = 0$.",
      "choices": [
        "$u = -6, u = -1$",
        "$u = 6, u = 1$",
        "$u = -6, u = 1$",
        "$u = 6, u = -1$"
      ],
      "answer": "$u = -6, u = -1$",
      "points": 10
    },
    {
      "id": 16,
      "wave": 1,
      "question": "Solve for $v$: $v^2 - 25 = 0$.",
      "choices": ["$v = 5, v = -5$", "$v = 25$", "$v = -25$", "$v = 0$"],
      "answer": "$v = 5, v = -5$",
      "points": 10
    },
    {
      "id": 17,
      "wave": 1,
      "question": "Solve for $w$: $w^2 - 6w + 8 = 0$.",
      "choices": [
        "$w = 2, w = 4$",
        "$w = -2, w = -4$",
        "$w = 2, w = -4$",
        "$w = -2, w = 4$"
      ],
      "answer": "$w = 2, w = 4$",
      "points": 10
    },
    {
      "id": 18,
      "wave": 1,
      "question": "Solve for $x$: $x^2 + 9x + 18 = 0$.",
      "choices": [
        "$x = -3, x = -6$",
        "$x = 3, x = 6$",
        "$x = -3, x = 6$",
        "$x = 3, x = -6$"
      ],
      "answer": "$x = -3, x = -6$",
      "points": 10
    },
    {
      "id": 19,
      "wave": 1,
      "question": "Solve for $y$: $y^2 - 10y + 24 = 0$.",
      "choices": [
        "$y = 4, y = 6$",
        "$y = -4, y = -6$",
        "$y = 4, y = -6$",
        "$y = -4, y = 6$"
      ],
      "answer": "$y = 4, y = 6$",
      "points": 10
    },
    {
      "id": 20,
      "wave": 1,
      "question": "Solve for $z$: $z^2 + 2z - 15 = 0$.",
      "choices": [
        "$z = 3, z = -5$",
        "$z = -3, z = 5$",
        "$z = 3, z = 5$",
        "$z = -3, z = -5$"
      ],
      "answer": "$z = 3, z = -5$",
      "points": 10
    },
    {
      "id": 21,
      "wave": 1,
      "question": "Solve for $a$: $a^2 - a - 12 = 0$.",
      "choices": [
        "$a = 4, a = -3$",
        "$a = -4, a = 3$",
        "$a = 4, a = 3$",
        "$a = -4, a = -3$"
      ],
      "answer": "$a = 4, a = -3$",
      "points": 10
    },
    {
      "id": 22,
      "wave": 1,
      "question": "Solve for $b$: $b^2 - 49 = 0$.",
      "choices": ["$b = 7, b = -7$", "$b = 49$", "$b = -49$", "$b = 0$"],
      "answer": "$b = 7, b = -7$",
      "points": 10
    },
    {
      "id": 23,
      "wave": 1,
      "question": "Solve for $c$: $c^2 + 10c + 25 = 0$.",
      "choices": ["$c = -5$", "$c = 5$", "$c = -5, c = -5$", "$c = 5, c = 5$"],
      "answer": "$c = -5$",
      "points": 10
    },
    {
      "id": 24,
      "wave": 1,
      "question": "Solve for $d$: $d^2 - 8d + 16 = 0$.",
      "choices": ["$d = 4$", "$d = -4$", "$d = 4, d = 4$", "$d = -4, d = -4$"],
      "answer": "$d = 4$",
      "points": 10
    },
    {
      "id": 25,
      "wave": 1,
      "question": "Solve for $e$: $e^2 - 100 = 0$.",
      "choices": ["$e = 10, e = -10$", "$e = 100$", "$e = -100$", "$e = 0$"],
      "answer": "$e = 10, e = -10$",
      "points": 10
    },
    {
      "id": 26,
      "wave": 1,
      "question": "Solve for $f$: $f^2 + 11f + 28 = 0$.",
      "choices": [
        "$f = -4, f = -7$",
        "$f = 4, f = 7$",
        "$f = -4, f = 7$",
        "$f = 4, f = -7$"
      ],
      "answer": "$f = -4, f = -7$",
      "points": 10
    },
    {
      "id": 27,
      "wave": 1,
      "question": "Solve for $g$: $g^2 - 12g + 36 = 0$.",
      "choices": ["$g = 6$", "$g = -6$", "$g = 6, g = 6$", "$g = -6, g = -6$"],
      "answer": "$g = 6$",
      "points": 10
    },
    {
      "id": 28,
      "wave": 1,
      "question": "Solve for $h$: $h^2 - 64 = 0$.",
      "choices": ["$h = 8, h = -8$", "$h = 64$", "$h = -64$", "$h = 0$"],
      "answer": "$h = 8, h = -8$",
      "points": 10
    },
    {
      "id": 29,
      "wave": 1,
      "question": "Solve for $i$: $i^2 + 12i + 35 = 0$.",
      "choices": [
        "$i = -5, i = -7$",
        "$i = 5, i = 7$",
        "$i = -5, i = 7$",
        "$i = 5, i = -7$"
      ],
      "answer": "$i = -5, i = -7$",
      "points": 10
    },
    {
      "id": 30,
      "wave": 1,
      "question": "Solve for $j$: $j^2 - 2j - 24 = 0$.",
      "choices": [
        "$j = 6, j = -4$",
        "$j = -6, j = 4$",
        "$j = 6, j = 4$",
        "$j = -6, j = -4$"
      ],
      "answer": "$j = 6, j = -4$",
      "points": 10
    },
    {
      "id": 31,
      "wave": 1,
      "question": "Solve for $k$: $k^2 + 3k - 10 = 0$.",
      "choices": [
        "$k = 2, k = -5$",
        "$k = -2, k = 5$",
        "$k = 2, k = 5$",
        "$k = -2, k = -5$"
      ],
      "answer": "$k = 2, k = -5$",
      "points": 10
    },
    {
      "id": 32,
      "wave": 1,
      "question": "Solve for $l$: $l^2 - 11l + 30 = 0$.",
      "choices": [
        "$l = 5, l = 6$",
        "$l = -5, l = -6$",
        "$l = 5, l = -6$",
        "$l = -5, l = 6$"
      ],
      "answer": "$l = 5, l = 6$",
      "points": 10
    },
    {
      "id": 33,
      "wave": 1,
      "question": "Solve for $m$: $m^2 + 13m + 40 = 0$.",
      "choices": [
        "$m = -5, m = -8$",
        "$m = 5, m = 8$",
        "$m = -5, m = 8$",
        "$m = 5, m = -8$"
      ],
      "answer": "$m = -5, m = -8$",
      "points": 10
    },
    {
      "id": 34,
      "wave": 1,
      "question": "Solve for $n$: $n^2 - 14n + 49 = 0$.",
      "choices": ["$n = 7$", "$n = -7$", "$n = 7, n = 7$", "$n = -7, n = -7$"],
      "answer": "$n = 7$",
      "points": 10
    },
    {
      "id": 35,
      "wave": 1,
      "question": "Solve for $p$: $p^2 - 81 = 0$.",
      "choices": ["$p = 9, p = -9$", "$p = 81$", "$p = -81$", "$p = 0$"],
      "answer": "$p = 9, p = -9$",
      "points": 10
    },
    {
      "id": 36,
      "wave": 1,
      "question": "Solve for $q$: $q^2 + 14q + 48 = 0$.",
      "choices": [
        "$q = -6, q = -8$",
        "$q = 6, q = 8$",
        "$q = -6, q = 8$",
        "$q = 6, q = -8$"
      ],
      "answer": "$q = -6, q = -8$",
      "points": 10
    },
    {
      "id": 37,
      "wave": 1,
      "question": "Solve for $r$: $r^2 - 9r + 20 = 0$.",
      "choices": [
        "$r = 4, r = 5$",
        "$r = -4, r = -5$",
        "$r = 4, r = -5$",
        "$r = -4, r = 5$"
      ],
      "answer": "$r = 4, r = 5$",
      "points": 10
    },
    {
      "id": 38,
      "wave": 1,
      "question": "Solve for $s$: $s^2 + 15s + 54 = 0$.",
      "choices": [
        "$s = -6, s = -9$",
        "$s = 6, s = 9$",
        "$s = -6, s = 9$",
        "$s = 6, s = -9$"
      ],
      "answer": "$s = -6, s = -9$",
      "points": 10
    },
    {
      "id": 39,
      "wave": 1,
      "question": "Solve for $t$: $t^2 - 13t + 42 = 0$.",
      "choices": [
        "$t = 6, t = 7$",
        "$t = -6, t = -7$",
        "$t = 6, t = -7$",
        "$t = -6, t = 7$"
      ],
      "answer": "$t = 6, t = 7$",
      "points": 10
    },
    {
      "id": 40,
      "wave": 1,
      "question": "Solve for $u$: $u^2 + 4u - 21 = 0$.",
      "choices": [
        "$u = 3, u = -7$",
        "$u = -3, u = 7$",
        "$u = 3, u = 7$",
        "$u = -3, u = -7$"
      ],
      "answer": "$u = 3, u = -7$",
      "points": 10
    },
    {
      "id": 41,
      "wave": 1,
      "question": "Solve for $v$: $v^2 - 5v - 14 = 0$.",
      "choices": [
        "$v = 7, v = -2$",
        "$v = -7, v = 2$",
        "$v = 7, v = 2$",
        "$v = -7, v = -2$"
      ],
      "answer": "$v = 7, v = -2$",
      "points": 10
    },
    {
      "id": 42,
      "wave": 1,
      "question": "Solve for $w$: $w^2 + 16w + 64 = 0$.",
      "choices": ["$w = -8$", "$w = 8$", "$w = -8, w = -8$", "$w = 8, w = 8$"],
      "answer": "$w = -8$",
      "points": 10
    },
    {
      "id": 43,
      "wave": 1,
      "question": "Solve for $x$: $x^2 - 121 = 0$.",
      "choices": ["$x = 11, x = -11$", "$x = 121$", "$x = -121$", "$x = 0$"],
      "answer": "$x = 11, x = -11$",
      "points": 10
    },
    {
      "id": 44,
      "wave": 1,
      "question": "Solve for $y$: $y^2 + 16y + 63 = 0$.",
      "choices": [
        "$y = -7, y = -9$",
        "$y = 7, y = 9$",
        "$y = -7, y = 9$",
        "$y = 7, y = -9$"
      ],
      "answer": "$y = -7, y = -9$",
      "points": 10
    },
    {
      "id": 45,
      "wave": 1,
      "question": "Solve for $z$: $z^2 - 15z + 56 = 0$.",
      "choices": [
        "$z = 7, z = 8$",
        "$z = -7, z = -8$",
        "$z = 7, z = -8$",
        "$z = -7, z = 8$"
      ],
      "answer": "$z = 7, z = 8$",
      "points": 10
    },
    {
      "id": 46,
      "wave": 1,
      "question": "Solve for $a$: $a^2 + 17a + 72 = 0$.",
      "choices": [
        "$a = -8, a = -9$",
        "$a = 8, a = 9$",
        "$a = -8, a = 9$",
        "$a = 8, a = -9$"
      ],
      "answer": "$a = -8, a = -9$",
      "points": 10
    },
    {
      "id": 47,
      "wave": 1,
      "question": "Solve for $b$: $b^2 - 18b + 81 = 0$.",
      "choices": ["$b = 9$", "$b = -9$", "$b = 9, b = 9$", "$b = -9, b = -9$"],
      "answer": "$b = 9$",
      "points": 10
    },
    {
      "id": 48,
      "wave": 1,
      "question": "Solve for $c$: $c^2 - 144 = 0$.",
      "choices": ["$c = 12, c = -12$", "$c = 144$", "$c = -144$", "$c = 0$"],
      "answer": "$c = 12, c = -12$",
      "points": 10
    },
    {
      "id": 49,
      "wave": 1,
      "question": "Solve for $d$: $d^2 + 18d + 77 = 0$.",
      "choices": [
        "$d = -7, d = -11$",
        "$d = 7, d = 11$",
        "$d = -7, d = 11$",
        "$d = 7, d = -11$"
      ],
      "answer": "$d = -7, d = -11$",
      "points": 10
    },
    {
      "id": 50,
      "wave": 1,
      "question": "Solve for $e$: $e^2 - 16e + 60 = 0$.",
      "choices": [
        "$e = 6, e = 10$",
        "$e = -6, e = -10$",
        "$e = 6, e = -10$",
        "$e = -6, e = 10$"
      ],
      "answer": "$e = 6, e = 10$",
      "points": 10
    },
    {
      "id": 51,
      "wave": 2,
      "question": "Solve for $x$: $3x^2 - 12x = 0$.",
      "choices": ["$x = 0, x = 4$", "$x = 0, x = -4$", "$x = 4$", "$x = -4$"],
      "answer": "$x = 0, x = 4$",
      "points": 15
    },
    {
      "id": 52,
      "wave": 2,
      "question": "Solve for $y$: $-2y^2 + 8y = 0$.",
      "choices": ["$y = 0, y = 4$", "$y = 0, y = -4$", "$y = 4$", "$y = -4$"],
      "answer": "$y = 0, y = 4$",
      "points": 15
    },
    {
      "id": 53,
      "wave": 2,
      "question": "Solve for $a$: $4a^2 - 36 = 0$.",
      "choices": ["$a = 3, a = -3$", "$a = 9, a = -9$", "$a = 3$", "$a = -3$"],
      "answer": "$a = 3, a = -3$",
      "points": 15
    },
    {
      "id": 54,
      "wave": 2,
      "question": "Solve for $b$: $b^2 + 14b + 49 = 0$.",
      "choices": ["$b = -7$", "$b = 7$", "$b = -7, b = -7$", "$b = 7, b = 7$"],
      "answer": "$b = -7$",
      "points": 15
    },
    {
      "id": 55,
      "wave": 2,
      "question": "Solve for $c$: $2c^2 + 10c + 12 = 0$.",
      "choices": [
        "$c = -2, c = -3$",
        "$c = 2, c = 3$",
        "$c = -2, c = 3$",
        "$c = 2, c = -3$"
      ],
      "answer": "$c = -2, c = -3$",
      "points": 15
    },
    {
      "id": 56,
      "wave": 2,
      "question": "Solve for $x$: $x^2 - 2x = 15$.",
      "choices": [
        "$x = 5, x = -3$",
        "$x = -5, x = 3$",
        "$x = 5, x = 3$",
        "$x = -5, x = -3$"
      ],
      "answer": "$x = 5, x = -3$",
      "points": 15
    },
    {
      "id": 57,
      "wave": 2,
      "question": "Solve for $y$: $y^2 + 6y = -8$.",
      "choices": [
        "$y = -2, y = -4$",
        "$y = 2, y = 4$",
        "$y = -2, y = 4$",
        "$y = 2, y = -4$"
      ],
      "answer": "$y = -2, y = -4$",
      "points": 15
    },
    {
      "id": 58,
      "wave": 2,
      "question": "Solve for $m$: $m^2 = 4m + 12$.",
      "choices": [
        "$m = 6, m = -2$",
        "$m = -6, m = 2$",
        "$m = 6, m = 2$",
        "$m = -6, m = -2$"
      ],
      "answer": "$m = 6, m = -2$",
      "points": 15
    },
    {
      "id": 59,
      "wave": 2,
      "question": "Solve for $n$: $2n^2 - 18 = 0$.",
      "choices": ["$n = 3, n = -3$", "$n = 9, n = -9$", "$n = 3$", "$n = -3$"],
      "answer": "$n = 3, n = -3$",
      "points": 15
    },
    {
      "id": 60,
      "wave": 2,
      "question": "Solve for $p$: $p^2 - 10p + 25 = 0$.",
      "choices": ["$p = 5$", "$p = -5$", "$p = 5, p = 5$", "$p = -5, p = -5$"],
      "answer": "$p = 5$",
      "points": 15
    },
    {
      "id": 61,
      "wave": 2,
      "question": "Solve for $q$: $3q^2 + 21q + 30 = 0$.",
      "choices": [
        "$q = -2, q = -5$",
        "$q = 2, q = 5$",
        "$q = -2, q = 5$",
        "$q = 2, q = -5$"
      ],
      "answer": "$q = -2, q = -5$",
      "points": 15
    },
    {
      "id": 62,
      "wave": 2,
      "question": "Solve for $r$: $r^2 + 18r + 81 = 0$.",
      "choices": ["$r = -9$", "$r = 9$", "$r = -9, r = -9$", "$r = 9, r = 9$"],
      "answer": "$r = -9$",
      "points": 15
    },
    {
      "id": 63,
      "wave": 2,
      "question": "Solve for $s$: $5s^2 - 45 = 0$.",
      "choices": ["$s = 3, s = -3$", "$s = 9, s = -9$", "$s = 3$", "$s = -3$"],
      "answer": "$s = 3, s = -3$",
      "points": 15
    },
    {
      "id": 64,
      "wave": 2,
      "question": "Solve for $t$: $t^2 - 16t + 64 = 0$.",
      "choices": ["$t = 8$", "$t = -8$", "$t = 8, t = 8$", "$t = -8, t = -8$"],
      "answer": "$t = 8$",
      "points": 15
    },
    {
      "id": 65,
      "wave": 2,
      "question": "Solve for $u$: $4u^2 + 20u + 24 = 0$.",
      "choices": [
        "$u = -2, u = -3$",
        "$u = 2, u = 3$",
        "$u = -2, u = 3$",
        "$u = 2, u = -3$"
      ],
      "answer": "$u = -2, u = -3$",
      "points": 15
    },
    {
      "id": 66,
      "wave": 2,
      "question": "Solve for $v$: $v^2 + 5v = -6$.",
      "choices": [
        "$v = -2, v = -3$",
        "$v = 2, v = 3$",
        "$v = -2, v = 3$",
        "$v = 2, v = -3$"
      ],
      "answer": "$v = -2, v = -3$",
      "points": 15
    },
    {
      "id": 67,
      "wave": 2,
      "question": "Solve for $w$: $w^2 = 10w - 24$.",
      "choices": [
        "$w = 4, w = 6$",
        "$w = -4, w = -6$",
        "$w = 4, w = -6$",
        "$w = -4, w = 6$"
      ],
      "answer": "$w = 4, w = 6$",
      "points": 15
    },
    {
      "id": 68,
      "wave": 2,
      "question": "Solve for $x$: $x^2 - 9x = -18$.",
      "choices": [
        "$x = 3, x = 6$",
        "$x = -3, x = -6$",
        "$x = 3, x = -6$",
        "$x = -3, x = 6$"
      ],
      "answer": "$x = 3, x = 6$",
      "points": 15
    },
    {
      "id": 69,
      "wave": 2,
      "question": "Solve for $y$: $-y^2 + 10y = 25$.",
      "choices": ["$y = 5$", "$y = -5$", "$y = 5, y = 5$", "$y = -5, y = -5$"],
      "answer": "$y = 5$",
      "points": 15
    },
    {
      "id": 70,
      "wave": 2,
      "question": "Solve for $z$: $6z^2 - 24 = 0$.",
      "choices": ["$z = 2, z = -2$", "$z = 4, z = -4$", "$z = 2$", "$z = -2$"],
      "answer": "$z = 2, z = -2$",
      "points": 15
    },
    {
      "id": 71,
      "wave": 2,
      "question": "Solve for $a$: $a^2 - 12a + 36 = 0$.",
      "choices": ["$a = 6$", "$a = -6$", "$a = 6, a = 6$", "$a = -6, a = -6$"],
      "answer": "$a = 6$",
      "points": 15
    },
    {
      "id": 72,
      "wave": 2,
      "question": "Solve for $b$: $2b^2 + 14b + 20 = 0$.",
      "choices": [
        "$b = -2, b = -5$",
        "$b = 2, b = 5$",
        "$b = -2, b = 5$",
        "$b = 2, b = -5$"
      ],
      "answer": "$b = -2, b = -5$",
      "points": 15
    },
    {
      "id": 73,
      "wave": 2,
      "question": "Solve for $c$: $c^2 + 20c + 100 = 0$.",
      "choices": [
        "$c = -10$",
        "$c = 10$",
        "$c = -10, c = -10$",
        "$c = 10, c = 10$"
      ],
      "answer": "$c = -10$",
      "points": 15
    },
    {
      "id": 74,
      "wave": 2,
      "question": "Solve for $d$: $7d^2 - 63 = 0$.",
      "choices": ["$d = 3, d = -3$", "$d = 9, d = -9$", "$d = 3$", "$d = -3$"],
      "answer": "$d = 3, d = -3$",
      "points": 15
    },
    {
      "id": 75,
      "wave": 2,
      "question": "Solve for $e$: $e^2 - 18e + 81 = 0$.",
      "choices": ["$e = 9$", "$e = -9$", "$e = 9, e = 9$", "$e = -9, e = -9$"],
      "answer": "$e = 9$",
      "points": 15
    },
    {
      "id": 76,
      "wave": 2,
      "question": "Solve for $f$: $3f^2 + 15f + 18 = 0$.",
      "choices": [
        "$f = -2, f = -3$",
        "$f = 2, f = 3$",
        "$f = -2, f = 3$",
        "$f = 2, f = -3$"
      ],
      "answer": "$f = -2, f = -3$",
      "points": 15
    },
    {
      "id": 77,
      "wave": 2,
      "question": "Solve for $g$: $g^2 + 7g = 30$.",
      "choices": [
        "$g = 3, g = -10$",
        "$g = -3, g = 10$",
        "$g = 3, g = 10$",
        "$g = -3, g = -10$"
      ],
      "answer": "$g = 3, g = -10$",
      "points": 15
    },
    {
      "id": 78,
      "wave": 2,
      "question": "Solve for $h$: $h^2 = 13h - 42$.",
      "choices": [
        "$h = 6, h = 7$",
        "$h = -6, h = -7$",
        "$h = 6, h = -7$",
        "$h = -6, h = 7$"
      ],
      "answer": "$h = 6, h = 7$",
      "points": 15
    },
    {
      "id": 79,
      "wave": 2,
      "question": "Solve for $i$: $i^2 - 11i = -28$.",
      "choices": [
        "$i = 4, i = 7$",
        "$i = -4, i = -7$",
        "$i = 4, i = -7$",
        "$i = -4, i = 7$"
      ],
      "answer": "$i = 4, i = 7$",
      "points": 15
    },
    {
      "id": 80,
      "wave": 2,
      "question": "Solve for $j$: $-j^2 + 12j = 36$.",
      "choices": ["$j = 6$", "$j = -6$", "$j = 6, j = 6$", "$j = -6, j = -6$"],
      "answer": "$j = 6$",
      "points": 15
    },
    {
      "id": 81,
      "wave": 2,
      "question": "Solve for $k$: $8k^2 - 32 = 0$.",
      "choices": ["$k = 2, k = -2$", "$k = 4, k = -4$", "$k = 2$", "$k = -2$"],
      "answer": "$k = 2, k = -2$",
      "points": 15
    },
    {
      "id": 82,
      "wave": 2,
      "question": "Solve for $l$: $l^2 + 22l + 121 = 0$.",
      "choices": [
        "$l = -11$",
        "$l = 11$",
        "$l = -11, l = -11$",
        "$l = 11, l = 11$"
      ],
      "answer": "$l = -11$",
      "points": 15
    },
    {
      "id": 83,
      "wave": 2,
      "question": "Solve for $m$: $2m^2 + 22m + 60 = 0$.",
      "choices": [
        "$m = -5, m = -6$",
        "$m = 5, m = 6$",
        "$m = -5, m = 6$",
        "$m = 5, m = -6$"
      ],
      "answer": "$m = -5, m = -6$",
      "points": 15
    },
    {
      "id": 84,
      "wave": 2,
      "question": "Solve for $n$: $n^2 + 24n + 144 = 0$.",
      "choices": [
        "$n = -12$",
        "$n = 12$",
        "$n = -12, n = -12$",
        "$n = 12, n = 12$"
      ],
      "answer": "$n = -12$",
      "points": 15
    },
    {
      "id": 85,
      "wave": 2,
      "question": "Solve for $p$: $9p^2 - 81 = 0$.",
      "choices": ["$p = 3, p = -3$", "$p = 9, p = -9$", "$p = 3$", "$p = -3$"],
      "answer": "$p = 3, p = -3$",
      "points": 15
    },
    {
      "id": 86,
      "wave": 2,
      "question": "Solve for $q$: $q^2 - 20q + 100 = 0$.",
      "choices": [
        "$q = 10$",
        "$q = -10$",
        "$q = 10, q = 10$",
        "$q = -10, q = -10$"
      ],
      "answer": "$q = 10$",
      "points": 15
    },
    {
      "id": 87,
      "wave": 2,
      "question": "Solve for $r$: $5r^2 + 30r + 40 = 0$.",
      "choices": [
        "$r = -2, r = -4$",
        "$r = 2, r = 4$",
        "$r = -2, r = 4$",
        "$r = 2, r = -4$"
      ],
      "answer": "$r = -2, r = -4$",
      "points": 15
    },
    {
      "id": 88,
      "wave": 2,
      "question": "Solve for $s$: $s^2 + 15s = -54$.",
      "choices": [
        "$s = -6, s = -9$",
        "$s = 6, s = 9$",
        "$s = -6, s = 9$",
        "$s = 6, s = -9$"
      ],
      "answer": "$s = -6, s = -9$",
      "points": 15
    },
    {
      "id": 89,
      "wave": 2,
      "question": "Solve for $t$: $t^2 = 16t - 63$.",
      "choices": [
        "$t = 7, t = 9$",
        "$t = -7, t = -9$",
        "$t = 7, t = -9$",
        "$t = -7, t = 9$"
      ],
      "answer": "$t = 7, t = 9$",
      "points": 15
    },
    {
      "id": 90,
      "wave": 2,
      "question": "Solve for $u$: $u^2 - 17u = -72$.",
      "choices": [
        "$u = 8, u = 9$",
        "$u = -8, u = -9$",
        "$u = 8, u = -9$",
        "$u = -8, u = 9$"
      ],
      "answer": "$u = 8, u = 9$",
      "points": 15
    },
    {
      "id": 91,
      "wave": 2,
      "question": "Solve for $v$: $-v^2 + 14v = 49$.",
      "choices": ["$v = 7$", "$v = -7$", "$v = 7, v = 7$", "$v = -7, v = -7$"],
      "answer": "$v = 7$",
      "points": 15
    },
    {
      "id": 92,
      "wave": 2,
      "question": "Solve for $w$: $10w^2 - 10 = 0$.",
      "choices": [
        "$w = 1, w = -1$",
        "$w = 10, w = -10$",
        "$w = 1$",
        "$w = -1$"
      ],
      "answer": "$w = 1, w = -1$",
      "points": 15
    },
    {
      "id": 93,
      "wave": 2,
      "question": "Solve for $x$: $x^2 + 20x + 100 = 0$.",
      "choices": [
        "$x = -10$",
        "$x = 10$",
        "$x = -10, x = -10$",
        "$x = 10, x = 10$"
      ],
      "answer": "$x = -10$",
      "points": 15
    },
    {
      "id": 94,
      "wave": 2,
      "question": "Solve for $y$: $6y^2 + 30y + 36 = 0$.",
      "choices": [
        "$y = -2, y = -3$",
        "$y = 2, y = 3$",
        "$y = -2, y = 3$",
        "$y = 2, y = -3$"
      ],
      "answer": "$y = -2, y = -3$",
      "points": 15
    },
    {
      "id": 95,
      "wave": 2,
      "question": "Solve for $z$: $z^2 + 22z + 121 = 0$.",
      "choices": [
        "$z = -11$",
        "$z = 11$",
        "$z = -11, z = -11$",
        "$z = 11, z = 11$"
      ],
      "answer": "$z = -11$",
      "points": 15
    },
    {
      "id": 96,
      "wave": 2,
      "question": "Solve for $a$: $12a^2 - 48 = 0$.",
      "choices": ["$a = 2, a = -2$", "$a = 4, a = -4$", "$a = 2$", "$a = -2$"],
      "answer": "$a = 2, a = -2$",
      "points": 15
    },
    {
      "id": 97,
      "wave": 2,
      "question": "Solve for $b$: $b^2 - 24b + 144 = 0$.",
      "choices": [
        "$b = 12$",
        "$b = -12$",
        "$b = 12, b = 12$",
        "$b = -12, b = -12$"
      ],
      "answer": "$b = 12$",
      "points": 15
    },
    {
      "id": 98,
      "wave": 2,
      "question": "Solve for $c$: $7c^2 + 42c + 56 = 0$.",
      "choices": [
        "$c = -2, c = -4$",
        "$c = 2, c = 4$",
        "$c = -2, c = 4$",
        "$c = 2, c = -4$"
      ],
      "answer": "$c = -2, c = -4$",
      "points": 15
    },
    {
      "id": 99,
      "wave": 2,
      "question": "Solve for $d$: $d^2 + 19d = -84$.",
      "choices": [
        "$d = -7, d = -12$",
        "$d = 7, d = 12$",
        "$d = -7, d = 12$",
        "$d = 7, d = -12$"
      ],
      "answer": "$d = -7, d = -12$",
      "points": 15
    },
    {
      "id": 100,
      "wave": 2,
      "question": "Solve for $e$: $e^2 = 18e - 77$.",
      "choices": [
        "$e = 7, e = 11$",
        "$e = -7, e = -11$",
        "$e = 7, e = -11$",
        "$e = -7, e = 11$"
      ],
      "answer": "$e = 7, e = 11$",
      "points": 15
    },
    {
      "id": 101,
      "wave": 3,
      "question": "Solve for $x$: $x^3 + 2x^2 + 3x + 6 = 0$.",
      "choices": [
        "$x = -2$",
        "$x = 2$",
        "$x = -2, x = \\pm i\\sqrt{3}$",
        "$x = 2, x = \\pm i\\sqrt{3}$"
      ],
      "answer": "$x = -2$",
      "points": 20
    },
    {
      "id": 102,
      "wave": 3,
      "question": "Solve for $y$: $2y^3 - 4y^2 + 5y - 10 = 0$.",
      "choices": [
        "$y = 2$",
        "$y = -2$",
        "$y = 2, y = \\pm i\\sqrt{5/2}$",
        "$y = -2, y = \\pm i\\sqrt{5/2}$"
      ],
      "answer": "$y = 2$",
      "points": 20
    },
    {
      "id": 103,
      "wave": 3,
      "question": "Solve for $a$: $3a^2 + 15a + 18 = 0$.",
      "choices": [
        "$a = -2, a = -3$",
        "$a = 2, a = 3$",
        "$a = -2, a = 3$",
        "$a = 2, a = -3$"
      ],
      "answer": "$a = -2, a = -3$",
      "points": 20
    },
    {
      "id": 104,
      "wave": 3,
      "question": "Solve for $b$: $5b^2 - 20b + 20 = 0$.",
      "choices": ["$b = 2$", "$b = -2$", "$b = 2, b = 2$", "$b = -2, b = -2$"],
      "answer": "$b = 2$",
      "points": 20
    },
    {
      "id": 105,
      "wave": 3,
      "question": "Solve for $c$: $2x^2 + 8x - 10 = 0$.",
      "choices": [
        "$x = 1, x = -5$",
        "$x = -1, x = 5$",
        "$x = 1, x = 5$",
        "$x = -1, x = -5$"
      ],
      "answer": "$x = 1, x = -5$",
      "points": 20
    },
    {
      "id": 106,
      "wave": 3,
      "question": "Solve for $x$: $x^3 - 4x^2 - x + 4 = 0$.",
      "choices": [
        "$x = 4, x = 1, x = -1$",
        "$x = -4, x = 1, x = -1$",
        "$x = 4, x = 1$",
        "$x = 4, x = -1$"
      ],
      "answer": "$x = 4, x = 1, x = -1$",
      "points": 20
    },
    {
      "id": 107,
      "wave": 3,
      "question": "Solve for $y$: $3y^3 + 6y^2 - 2y - 4 = 0$.",
      "choices": [
        "$y = -2, y = \\pm \\frac{\\sqrt{6}}{3}$",
        "$y = 2, y = \\pm \\frac{\\sqrt{6}}{3}$",
        "$y = -2$",
        "$y = 2$"
      ],
      "answer": "$y = -2, y = \\pm \\frac{\\sqrt{6}}{3}$",
      "points": 20
    },
    {
      "id": 108,
      "wave": 3,
      "question": "Solve for $m$: $4m^2 - 24m + 36 = 0$.",
      "choices": ["$m = 3$", "$m = -3$", "$m = 3, m = 3$", "$m = -3, m = -3$"],
      "answer": "$m = 3$",
      "points": 20
    },
    {
      "id": 109,
      "wave": 3,
      "question": "Solve for $n$: $6n^2 - 12n - 18 = 0$.",
      "choices": [
        "$n = 3, n = -1$",
        "$n = -3, n = 1$",
        "$n = 3, n = 1$",
        "$n = -3, n = -1$"
      ],
      "answer": "$n = 3, n = -1$",
      "points": 20
    },
    {
      "id": 110,
      "wave": 3,
      "question": "Solve for $p$: $2p^2 + 10p + 8 = 0$.",
      "choices": [
        "$p = -1, p = -4$",
        "$p = 1, p = 4$",
        "$p = -1, p = 4$",
        "$p = 1, p = -4$"
      ],
      "answer": "$p = -1, p = -4$",
      "points": 20
    },
    {
      "id": 111,
      "wave": 3,
      "question": "Solve for $q$: $x^3 + 5x^2 - 4x - 20 = 0$.",
      "choices": [
        "$x = -5, x = 2, x = -2$",
        "$x = 5, x = 2, x = -2$",
        "$x = -5, x = 2$",
        "$x = -5, x = -2$"
      ],
      "answer": "$x = -5, x = 2, x = -2$",
      "points": 20
    },
    {
      "id": 112,
      "wave": 3,
      "question": "Solve for $r$: $r^2 + 2r = 15$.",
      "choices": [
        "$r = 3, r = -5$",
        "$r = -3, r = 5$",
        "$r = 3, r = 5$",
        "$r = -3, r = -5$"
      ],
      "answer": "$r = 3, r = -5$",
      "points": 20
    },
    {
      "id": 113,
      "wave": 3,
      "question": "Solve for $s$: $s^2 = 7s - 10$.",
      "choices": [
        "$s = 2, s = 5$",
        "$s = -2, s = -5$",
        "$s = 2, s = -5$",
        "$s = -2, s = 5$"
      ],
      "answer": "$s = 2, s = 5$",
      "points": 20
    },
    {
      "id": 114,
      "wave": 3,
      "question": "Solve for $t$: $3t^2 - 15t + 18 = 0$.",
      "choices": [
        "$t = 2, t = 3$",
        "$t = -2, t = -3$",
        "$t = 2, t = -3$",
        "$t = -2, t = 3$"
      ],
      "answer": "$t = 2, t = 3$",
      "points": 20
    },
    {
      "id": 115,
      "wave": 3,
      "question": "Solve for $u$: $u^2 + 10u = -25$.",
      "choices": ["$u = -5$", "$u = 5$", "$u = -5, u = -5$", "$u = 5, u = 5$"],
      "answer": "$u = -5$",
      "points": 20
    },
    {
      "id": 116,
      "wave": 3,
      "question": "Solve for $v$: $v^3 - 3v^2 + 2v - 6 = 0$.",
      "choices": [
        "$v = 3$",
        "$v = -3$",
        "$v = 3, v = \\pm i\\sqrt{2}$",
        "$v = -3, v = \\pm i\\sqrt{2}$"
      ],
      "answer": "$v = 3$",
      "points": 20
    },
    {
      "id": 117,
      "wave": 3,
      "question": "Solve for $w$: $5w^2 + 30w + 45 = 0$.",
      "choices": ["$w = -3$", "$w = 3$", "$w = -3, w = -3$", "$w = 3, w = 3$"],
      "answer": "$w = -3$",
      "points": 20
    },
    {
      "id": 118,
      "wave": 3,
      "question": "Solve for $x$: $x^2 + 11x = -28$.",
      "choices": [
        "$x = -4, x = -7$",
        "$x = 4, x = 7$",
        "$x = -4, x = 7$",
        "$x = 4, x = -7$"
      ],
      "answer": "$x = -4, x = -7$",
      "points": 20
    },
    {
      "id": 119,
      "wave": 3,
      "question": "Solve for $y$: $y^2 = 12y - 35$.",
      "choices": [
        "$y = 5, y = 7$",
        "$y = -5, y = -7$",
        "$y = 5, y = -7$",
        "$y = -5, y = 7$"
      ],
      "answer": "$y = 5, y = 7$",
      "points": 20
    },
    {
      "id": 120,
      "wave": 3,
      "question": "Solve for $z$: $2z^2 - 2z - 24 = 0$.",
      "choices": [
        "$z = 4, z = -3$",
        "$z = -4, z = 3$",
        "$z = 4, z = 3$",
        "$z = -4, z = -3$"
      ],
      "answer": "$z = 4, z = -3$",
      "points": 20
    },
    {
      "id": 121,
      "wave": 3,
      "question": "Solve for $a$: $a^3 - 2a^2 + 5a - 10 = 0$.",
      "choices": [
        "$a = 2$",
        "$a = -2$",
        "$a = 2, a = \\pm i\\sqrt{5}$",
        "$a = -2, a = \\pm i\\sqrt{5}$"
      ],
      "answer": "$a = 2$",
      "points": 20
    },
    {
      "id": 122,
      "wave": 3,
      "question": "Solve for $b$: $7b^2 + 28b + 28 = 0$.",
      "choices": ["$b = -2$", "$b = 2$", "$b = -2, b = -2$", "$b = 2, b = 2$"],
      "answer": "$b = -2$",
      "points": 20
    },
    {
      "id": 123,
      "wave": 3,
      "question": "Solve for $c$: $2c^2 + 22c + 48 = 0$.",
      "choices": [
        "$c = -3, c = -8$",
        "$c = 3, c = 8$",
        "$c = -3, c = 8$",
        "$c = 3, c = -8$"
      ],
      "answer": "$c = -3, c = -8$",
      "points": 20
    },
    {
      "id": 124,
      "wave": 3,
      "question": "Solve for $d$: $d^2 + 24d + 144 = 0$.",
      "choices": [
        "$d = -12$",
        "$d = 12$",
        "$d = -12, d = -12$",
        "$d = 12, d = 12$"
      ],
      "answer": "$d = -12$",
      "points": 20
    },
    {
      "id": 125,
      "wave": 3,
      "question": "Solve for $e$: $e^3 + e^2 - 9e - 9 = 0$.",
      "choices": [
        "$e = -1, e = 3, e = -3$",
        "$e = 1, e = 3, e = -3$",
        "$e = -1, e = 3$",
        "$e = -1, e = -3$"
      ],
      "answer": "$e = -1, e = 3, e = -3$",
      "points": 20
    },
    {
      "id": 126,
      "wave": 3,
      "question": "Solve for $f$: $f^2 + 13f = -40$.",
      "choices": [
        "$f = -5, f = -8$",
        "$f = 5, f = 8$",
        "$f = -5, f = 8$",
        "$f = 5, f = -8$"
      ],
      "answer": "$f = -5, f = -8$",
      "points": 20
    },
    {
      "id": 127,
      "wave": 3,
      "question": "Solve for $g$: $g^2 = 14g - 49$.",
      "choices": ["$g = 7$", "$g = -7$", "$g = 7, g = 7$", "$g = -7, g = -7$"],
      "answer": "$g = 7$",
      "points": 20
    },
    {
      "id": 128,
      "wave": 3,
      "question": "Solve for $h$: $3h^2 - 39h + 126 = 0$.",
      "choices": [
        "$h = 6, h = 7$",
        "$h = -6, h = -7$",
        "$h = 6, h = -7$",
        "$h = -6, h = 7$"
      ],
      "answer": "$h = 6, h = 7$",
      "points": 20
    },
    {
      "id": 129,
      "wave": 3,
      "question": "Solve for $i$: $i^2 + 25i + 100 = 0$.",
      "choices": [
        "$i = -5, i = -20$",
        "$i = 5, i = 20$",
        "$i = -5, i = 20$",
        "$i = 5, i = -20$"
      ],
      "answer": "$i = -5, i = -20$",
      "points": 20
    },
    {
      "id": 130,
      "wave": 3,
      "question": "Solve for $j$: $j^3 - 6j^2 + 4j - 24 = 0$.",
      "choices": [
        "$j = 6$",
        "$j = -6$",
        "$j = 6, j = \\pm 2i$",
        "$j = -6, j = \\pm 2i$"
      ],
      "answer": "$j = 6$",
      "points": 20
    },
    {
      "id": 131,
      "wave": 3,
      "question": "Solve for $k$: $k^2 + 15k = -54$.",
      "choices": [
        "$k = -6, k = -9$",
        "$k = 6, k = 9$",
        "$k = -6, k = 9$",
        "$k = 6, k = -9$"
      ],
      "answer": "$k = -6, k = -9$",
      "points": 20
    },
    {
      "id": 132,
      "wave": 3,
      "question": "Solve for $l$: $l^2 = 16l - 60$.",
      "choices": [
        "$l = 6, l = 10$",
        "$l = -6, l = -10$",
        "$l = 6, l = -10$",
        "$l = -6, l = 10$"
      ],
      "answer": "$l = 6, l = 10$",
      "points": 20
    },
    {
      "id": 133,
      "wave": 3,
      "question": "Solve for $m$: $4m^2 - 4m - 24 = 0$.",
      "choices": [
        "$m = 3, m = -2$",
        "$m = -3, m = 2$",
        "$m = 3, m = 2$",
        "$m = -3, m = -2$"
      ],
      "answer": "$m = 3, m = -2$",
      "points": 20
    },
    {
      "id": 134,
      "wave": 3,
      "question": "Solve for $n$: $n^2 + 26n + 169 = 0$.",
      "choices": [
        "$n = -13$",
        "$n = 13$",
        "$n = -13, n = -13$",
        "$n = 13, n = 13$"
      ],
      "answer": "$n = -13$",
      "points": 20
    },
    {
      "id": 135,
      "wave": 3,
      "question": "Solve for $p$: $p^3 + 4p^2 - 2p - 8 = 0$.",
      "choices": [
        "$p = -4, p = \\sqrt{2}, p = -\\sqrt{2}$",
        "$p = 4, p = \\sqrt{2}, p = -\\sqrt{2}$",
        "$p = -4$",
        "$p = 4$"
      ],
      "answer": "$p = -4, p = \\sqrt{2}, p = -\\sqrt{2}$",
      "points": 20
    },
    {
      "id": 136,
      "wave": 3,
      "question": "Solve for $q$: $q^2 + 17q = -72$.",
      "choices": [
        "$q = -8, q = -9$",
        "$q = 8, q = 9$",
        "$q = -8, q = 9$",
        "$q = 8, q = -9$"
      ],
      "answer": "$q = -8, q = -9$",
      "points": 20
    },
    {
      "id": 137,
      "wave": 3,
      "question": "Solve for $r$: $r^2 = 18r - 81$.",
      "choices": ["$r = 9$", "$r = -9$", "$r = 9, r = 9$", "$r = -9, r = -9$"],
      "answer": "$r = 9$",
      "points": 20
    },
    {
      "id": 138,
      "wave": 3,
      "question": "Solve for $s$: $5s^2 - 25s + 30 = 0$.",
      "choices": [
        "$s = 2, s = 3$",
        "$s = -2, s = -3$",
        "$s = 2, s = -3$",
        "$s = -2, s = 3$"
      ],
      "answer": "$s = 2, s = 3$",
      "points": 20
    },
    {
      "id": 139,
      "wave": 3,
      "question": "Solve for $t$: $t^2 + 20t + 96 = 0$.",
      "choices": [
        "$t = -8, t = -12$",
        "$t = 8, t = 12$",
        "$t = -8, t = 12$",
        "$t = 8, t = -12$"
      ],
      "answer": "$t = -8, t = -12$",
      "points": 20
    },
    {
      "id": 140,
      "wave": 3,
      "question": "Solve for $u$: $u^3 - 5u^2 + 3u - 15 = 0$.",
      "choices": [
        "$u = 5$",
        "$u = -5$",
        "$u = 5, u = \\pm i\\sqrt{3}$",
        "$u = -5, u = \\pm i\\sqrt{3}$"
      ],
      "answer": "$u = 5$",
      "points": 20
    },
    {
      "id": 141,
      "wave": 3,
      "question": "Solve for $v$: $v^2 + 28v + 196 = 0$.",
      "choices": [
        "$v = -14$",
        "$v = 14$",
        "$v = -14, v = -14$",
        "$v = 14, v = 14$"
      ],
      "answer": "$v = -14$",
      "points": 20
    },
    {
      "id": 142,
      "wave": 3,
      "question": "Solve for $w$: $6w^2 + 36w + 48 = 0$.",
      "choices": [
        "$w = -2, w = -4$",
        "$w = 2, w = 4$",
        "$w = -2, w = 4$",
        "$w = 2, w = -4$"
      ],
      "answer": "$w = -2, w = -4$",
      "points": 20
    },
    {
      "id": 143,
      "wave": 3,
      "question": "Solve for $x$: $x^2 + 19x = -84$.",
      "choices": [
        "$x = -7, x = -12$",
        "$x = 7, x = 12$",
        "$x = -7, x = 12$",
        "$x = 7, x = -12$"
      ],
      "answer": "$x = -7, x = -12$",
      "points": 20
    },
    {
      "id": 144,
      "wave": 3,
      "question": "Solve for $y$: $y^2 = 20y - 96$.",
      "choices": [
        "$y = 8, y = 12$",
        "$y = -8, y = -12$",
        "$y = 8, y = -12$",
        "$y = -8, y = 12$"
      ],
      "answer": "$y = 8, y = 12$",
      "points": 20
    },
    {
      "id": 145,
      "wave": 3,
      "question": "Solve for $z$: $2z^2 - 28z + 98 = 0$.",
      "choices": ["$z = 7$", "$z = -7$", "$z = 7, z = 7$", "$z = -7, z = -7$"],
      "answer": "$z = 7$",
      "points": 20
    },
    {
      "id": 146,
      "wave": 3,
      "question": "Solve for $a$: $a^3 + 3a^2 - 4a - 12 = 0$.",
      "choices": [
        "$a = -3, a = 2, a = -2$",
        "$a = 3, a = 2, a = -2$",
        "$a = -3, a = 2$",
        "$a = -3, a = -2$"
      ],
      "answer": "$a = -3, a = 2, a = -2$",
      "points": 20
    },
    {
      "id": 147,
      "wave": 3,
      "question": "Solve for $b$: $8b^2 + 40b + 48 = 0$.",
      "choices": [
        "$b = -2, b = -3$",
        "$b = 2, b = 3$",
        "$b = -2, b = 3$",
        "$b = 2, b = -3$"
      ],
      "answer": "$b = -2, b = -3$",
      "points": 20
    },
    {
      "id": 148,
      "wave": 3,
      "question": "Solve for $c$: $c^2 + 21c = -90$.",
      "choices": [
        "$c = -6, c = -15$",
        "$c = 6, c = 15$",
        "$c = -6, c = 15$",
        "$c = 6, c = -15$"
      ],
      "answer": "$c = -6, c = -15$",
      "points": 20
    },
    {
      "id": 149,
      "wave": 3,
      "question": "Solve for $d$: $d^2 = 22d - 121$.",
      "choices": [
        "$d = 11$",
        "$d = -11$",
        "$d = 11, d = 11$",
        "$d = -11, d = -11$"
      ],
      "answer": "$d = 11$",
      "points": 20
    },
    {
      "id": 150,
      "wave": 3,
      "question": "Solve for $e$: $e^3 - e^2 - 16e + 16 = 0$.",
      "choices": [
        "$e = 1, e = 4, e = -4$",
        "$e = -1, e = 4, e = -4$",
        "$e = 1, e = 4$",
        "$e = 1, e = -4$"
      ],
      "answer": "$e = 1, e = 4, e = -4$",
      "points": 20
    },
    {
      "id": 151,
      "wave": 4,
      "question": "Solve for $x$: $2x^3 + 6x^2 - 8x - 24 = 0$.",
      "choices": [
        "$x = -3, x = 2, x = -2$",
        "$x = 3, x = 2, x = -2$",
        "$x = -3, x = 2$",
        "$x = -3, x = -2$"
      ],
      "answer": "$x = -3, x = 2, x = -2$",
      "points": 25
    },
    {
      "id": 152,
      "wave": 4,
      "question": "Solve for $y$: $3y^3 - 9y^2 + 12y - 36 = 0$.",
      "choices": [
        "$y = 3$",
        "$y = -3$",
        "$y = 3, y = \\pm 2i$",
        "$y = -3, y = \\pm 2i$"
      ],
      "answer": "$y = 3$",
      "points": 25
    },
    {
      "id": 153,
      "wave": 4,
      "question": "Solve for $a$: $2a^2 - 10a + 12 = 0$.",
      "choices": [
        "$a = 2, a = 3$",
        "$a = -2, a = -3$",
        "$a = 2, a = -3$",
        "$a = -2, a = 3$"
      ],
      "answer": "$a = 2, a = 3$",
      "points": 25
    },
    {
      "id": 154,
      "wave": 4,
      "question": "Solve for $b$: $4b^2 - 16b + 16 = 0$.",
      "choices": ["$b = 2$", "$b = -2$", "$b = 2, b = 2$", "$b = -2, b = -2$"],
      "answer": "$b = 2$",
      "points": 25
    },
    {
      "id": 155,
      "wave": 4,
      "question": "Solve for $c$: $2x^2 + 14x + 24 = 0$.",
      "choices": [
        "$x = -3, x = -4$",
        "$x = 3, x = 4$",
        "$x = -3, x = 4$",
        "$x = 3, x = -4$"
      ],
      "answer": "$x = -3, x = -4$",
      "points": 25
    },
    {
      "id": 156,
      "wave": 4,
      "question": "Solve for $x$: $x^3 + 3x^2 - 16x - 48 = 0$.",
      "choices": [
        "$x = -3, x = 4, x = -4$",
        "$x = 3, x = 4, x = -4$",
        "$x = -3, x = 4$",
        "$x = -3, x = -4$"
      ],
      "answer": "$x = -3, x = 4, x = -4$",
      "points": 25
    },
    {
      "id": 157,
      "wave": 4,
      "question": "Solve for $y$: $5y^3 - 10y^2 + 20y - 40 = 0$.",
      "choices": [
        "$y = 2$",
        "$y = -2$",
        "$y = 2, y = \\pm 2i$",
        "$y = -2, y = \\pm 2i$"
      ],
      "answer": "$y = 2$",
      "points": 25
    },
    {
      "id": 158,
      "wave": 4,
      "question": "Solve for $m$: $6m^2 - 36m + 54 = 0$.",
      "choices": ["$m = 3$", "$m = -3$", "$m = 3, m = 3$", "$m = -3, m = -3$"],
      "answer": "$m = 3$",
      "points": 25
    },
    {
      "id": 159,
      "wave": 4,
      "question": "Solve for $n$: $3n^2 - 3n - 6 = 0$.",
      "choices": [
        "$n = 2, n = -1$",
        "$n = -2, n = 1$",
        "$n = 2, n = 1$",
        "$n = -2, n = -1$"
      ],
      "answer": "$n = 2, n = -1$",
      "points": 25
    },
    {
      "id": 160,
      "wave": 4,
      "question": "Solve for $p$: $2p^2 + 18p + 36 = 0$.",
      "choices": [
        "$p = -3, p = -6$",
        "$p = 3, p = 6$",
        "$p = -3, p = 6$",
        "$p = 3, p = -6$"
      ],
      "answer": "$p = -3, p = -6$",
      "points": 25
    },
    {
      "id": 161,
      "wave": 4,
      "question": "Solve for $q$: $q^3 + 6q^2 - 9q - 54 = 0$.",
      "choices": [
        "$q = -6, q = 3, q = -3$",
        "$q = 6, q = 3, q = -3$",
        "$q = -6, q = 3$",
        "$q = -6, q = -3$"
      ],
      "answer": "$q = -6, q = 3, q = -3$",
      "points": 25
    },
    {
      "id": 162,
      "wave": 4,
      "question": "Solve for $r$: $r^2 + 19r = -84$.",
      "choices": [
        "$r = -7, r = -12$",
        "$r = 7, r = 12$",
        "$r = -7, r = 12$",
        "$r = 7, r = -12$"
      ],
      "answer": "$r = -7, r = -12$",
      "points": 25
    },
    {
      "id": 163,
      "wave": 4,
      "question": "Solve for $s$: $s^2 = 20s - 96$.",
      "choices": [
        "$s = 8, s = 12$",
        "$s = -8, s = -12$",
        "$s = 8, s = -12$",
        "$s = -8, s = 12$"
      ],
      "answer": "$s = 8, s = 12$",
      "points": 25
    },
    {
      "id": 164,
      "wave": 4,
      "question": "Solve for $t$: $5t^2 - 35t + 60 = 0$.",
      "choices": [
        "$t = 3, t = 4$",
        "$t = -3, t = -4$",
        "$t = 3, t = -4$",
        "$t = -3, t = 4$"
      ],
      "answer": "$t = 3, t = 4$",
      "points": 25
    },
    {
      "id": 165,
      "wave": 4,
      "question": "Solve for $u$: $u^2 + 25u + 100 = 0$.",
      "choices": [
        "$u = -5, u = -20$",
        "$u = 5, u = 20$",
        "$u = -5, u = 20$",
        "$u = 5, u = -20$"
      ],
      "answer": "$u = -5, u = -20$",
      "points": 25
    },
    {
      "id": 166,
      "wave": 4,
      "question": "Solve for $v$: $v^3 - 2v^2 - 25v + 50 = 0$.",
      "choices": [
        "$v = 2, v = 5, v = -5$",
        "$v = -2, v = 5, v = -5$",
        "$v = 2, v = 5$",
        "$v = 2, v = -5$"
      ],
      "answer": "$v = 2, v = 5, v = -5$",
      "points": 25
    },
    {
      "id": 167,
      "wave": 4,
      "question": "Solve for $w$: $7w^2 + 42w + 63 = 0$.",
      "choices": ["$w = -3$", "$w = 3$", "$w = -3, w = -3$", "$w = 3, w = 3$"],
      "answer": "$w = -3$",
      "points": 25
    },
    {
      "id": 168,
      "wave": 4,
      "question": "Solve for $x$: $x^2 + 21x = -90$.",
      "choices": [
        "$x = -6, x = -15$",
        "$x = 6, x = 15$",
        "$x = -6, x = 15$",
        "$x = 6, x = -15$"
      ],
      "answer": "$x = -6, x = -15$",
      "points": 25
    },
    {
      "id": 169,
      "wave": 4,
      "question": "Solve for $y$: $y^2 = 22y - 121$.",
      "choices": [
        "$y = 11$",
        "$y = -11$",
        "$y = 11, y = 11$",
        "$y = -11, y = -11$"
      ],
      "answer": "$y = 11$",
      "points": 25
    },
    {
      "id": 170,
      "wave": 4,
      "question": "Solve for $z$: $2z^2 - 30z + 100 = 0$.",
      "choices": [
        "$z = 5, z = 10$",
        "$z = -5, z = -10$",
        "$z = 5, z = -10$",
        "$z = -5, z = 10$"
      ],
      "answer": "$z = 5, z = 10$",
      "points": 25
    },
    {
      "id": 171,
      "wave": 4,
      "question": "Solve for $a$: $a^3 + 5a^2 - 9a - 45 = 0$.",
      "choices": [
        "$a = -5, a = 3, a = -3$",
        "$a = 5, a = 3, a = -3$",
        "$a = -5, a = 3$",
        "$a = -5, a = -3$"
      ],
      "answer": "$a = -5, a = 3, a = -3$",
      "points": 25
    },
    {
      "id": 172,
      "wave": 4,
      "question": "Solve for $b$: $8b^2 + 48b + 72 = 0$.",
      "choices": ["$b = -3$", "$b = 3$", "$b = -3, b = -3$", "$b = 3, b = 3$"],
      "answer": "$b = -3$",
      "points": 25
    },
    {
      "id": 173,
      "wave": 4,
      "question": "Solve for $c$: $c^2 + 23c = -120$.",
      "choices": [
        "$c = -8, c = -15$",
        "$c = 8, c = 15$",
        "$c = -8, c = 15$",
        "$c = 8, c = -15$"
      ],
      "answer": "$c = -8, c = -15$",
      "points": 25
    },
    {
      "id": 174,
      "wave": 4,
      "question": "Solve for $d$: $d^2 = 24d - 144$.",
      "choices": [
        "$d = 12$",
        "$d = -12$",
        "$d = 12, d = 12$",
        "$d = -12, d = -12$"
      ],
      "answer": "$d = 12$",
      "points": 25
    },
    {
      "id": 175,
      "wave": 4,
      "question": "Solve for $e$: $3e^2 - 39e + 126 = 0$.",
      "choices": [
        "$e = 6, e = 7$",
        "$e = -6, e = -7$",
        "$e = 6, e = -7$",
        "$e = -6, e = 7$"
      ],
      "answer": "$e = 6, e = 7$",
      "points": 25
    },
    {
      "id": 176,
      "wave": 4,
      "question": "Solve for $f$: $f^3 - 3f^2 - 4f + 12 = 0$.",
      "choices": [
        "$f = 3, f = 2, f = -2$",
        "$f = -3, f = 2, f = -2$",
        "$f = 3, f = 2$",
        "$f = 3, f = -2$"
      ],
      "answer": "$f = 3, f = 2, f = -2$",
      "points": 25
    },
    {
      "id": 177,
      "wave": 4,
      "question": "Solve for $g$: $g^2 + 25g = -100$.",
      "choices": [
        "$g = -5, g = -20$",
        "$g = 5, g = 20$",
        "$g = -5, g = 20$",
        "$g = 5, g = -20$"
      ],
      "answer": "$g = -5, g = -20$",
      "points": 25
    },
    {
      "id": 178,
      "wave": 4,
      "question": "Solve for $h$: $h^2 = 26h - 169$.",
      "choices": [
        "$h = 13$",
        "$h = -13$",
        "$h = 13, h = 13$",
        "$h = -13, h = -13$"
      ],
      "answer": "$h = 13$",
      "points": 25
    },
    {
      "id": 179,
      "wave": 4,
      "question": "Solve for $i$: $4i^2 - 44i + 120 = 0$.",
      "choices": [
        "$i = 5, i = 6$",
        "$i = -5, i = -6$",
        "$i = 5, i = -6$",
        "$i = -5, i = 6$"
      ],
      "answer": "$i = 5, i = 6$",
      "points": 25
    },
    {
      "id": 180,
      "wave": 4,
      "question": "Solve for $j$: $j^3 + 2j^2 - 4j - 8 = 0$.",
      "choices": [
        "$j = -2, j = 2$",
        "$j = 2$",
        "$j = -2$",
        "$j = -2, j = 2, j = 2$"
      ],
      "answer": "$j = -2, j = 2$",
      "points": 25
    },
    {
      "id": 181,
      "wave": 4,
      "question": "Solve for $k$: $k^2 + 26k = -169$.",
      "choices": [
        "$k = -13$",
        "$k = 13$",
        "$k = -13, k = -13$",
        "$k = 13, k = 13$"
      ],
      "answer": "$k = -13$",
      "points": 25
    },
    {
      "id": 182,
      "wave": 4,
      "question": "Solve for $l$: $l^2 = 28l - 196$.",
      "choices": [
        "$l = 14$",
        "$l = -14$",
        "$l = 14, l = 14$",
        "$l = -14, l = -14$"
      ],
      "answer": "$l = 14$",
      "points": 25
    },
    {
      "id": 183,
      "wave": 4,
      "question": "Solve for $m$: $9m^2 - 9m - 18 = 0$.",
      "choices": [
        "$m = 2, m = -1$",
        "$m = -2, m = 1$",
        "$m = 2, m = 1$",
        "$m = -2, m = -1$"
      ],
      "answer": "$m = 2, m = -1$",
      "points": 25
    },
    {
      "id": 184,
      "wave": 4,
      "question": "Solve for $n$: $n^2 + 27n + 182 = 0$.",
      "choices": [
        "$n = -13, n = -14$",
        "$n = 13, n = 14$",
        "$n = -13, n = 14$",
        "$n = 13, n = -14$"
      ],
      "answer": "$n = -13, n = -14$",
      "points": 25
    },
    {
      "id": 185,
      "wave": 4,
      "question": "Solve for $p$: $p^3 - 4p^2 - 9p + 36 = 0$.",
      "choices": [
        "$p = 4, p = 3, p = -3$",
        "$p = -4, p = 3, p = -3$",
        "$p = 4, p = 3$",
        "$p = 4, p = -3$"
      ],
      "answer": "$p = 4, p = 3, p = -3$",
      "points": 25
    },
    {
      "id": 186,
      "wave": 4,
      "question": "Solve for $q$: $q^2 + 28q = -196$.",
      "choices": [
        "$q = -14$",
        "$q = 14$",
        "$q = -14, q = -14$",
        "$q = 14, q = 14$"
      ],
      "answer": "$q = -14$",
      "points": 25
    },
    {
      "id": 187,
      "wave": 4,
      "question": "Solve for $r$: $r^2 = 29r - 210$.",
      "choices": [
        "$r = 14, r = 15$",
        "$r = -14, r = -15$",
        "$r = 14, r = -15$",
        "$r = -14, r = 15$"
      ],
      "answer": "$r = 14, r = 15$",
      "points": 25
    },
    {
      "id": 188,
      "wave": 4,
      "question": "Solve for $s$: $6s^2 - 42s + 72 = 0$.",
      "choices": [
        "$s = 3, s = 4$",
        "$s = -3, s = -4$",
        "$s = 3, s = -4$",
        "$s = -3, s = 4$"
      ],
      "answer": "$s = 3, s = 4$",
      "points": 25
    },
    {
      "id": 189,
      "wave": 4,
      "question": "Solve for $t$: $t^2 + 29t + 210 = 0$.",
      "choices": [
        "$t = -14, t = -15$",
        "$t = 14, t = 15$",
        "$t = -14, t = 15$",
        "$t = 14, t = -15$"
      ],
      "answer": "$t = -14, t = -15$",
      "points": 25
    },
    {
      "id": 190,
      "wave": 4,
      "question": "Solve for $u$: $u^3 + 3u^2 - 25u - 75 = 0$.",
      "choices": [
        "$u = -3, u = 5, u = -5$",
        "$u = 3, u = 5, u = -5$",
        "$u = -3, u = 5$",
        "$u = -3, u = -5$"
      ],
      "answer": "$u = -3, u = 5, u = -5$",
      "points": 25
    },
    {
      "id": 191,
      "wave": 4,
      "question": "Solve for $v$: $v^2 + 30v + 225 = 0$.",
      "choices": [
        "$v = -15$",
        "$v = 15$",
        "$v = -15, v = -15$",
        "$v = 15, v = 15$"
      ],
      "answer": "$v = -15$",
      "points": 25
    },
    {
      "id": 192,
      "wave": 4,
      "question": "Solve for $w$: $10w^2 + 50w + 60 = 0$.",
      "choices": [
        "$w = -2, w = -3$",
        "$w = 2, w = 3$",
        "$w = -2, w = 3$",
        "$w = 2, w = -3$"
      ],
      "answer": "$w = -2, w = -3$",
      "points": 25
    },
    {
      "id": 193,
      "wave": 4,
      "question": "Solve for $x$: $x^2 + 30x = -225$.",
      "choices": [
        "$x = -15$",
        "$x = 15$",
        "$x = -15, x = -15$",
        "$x = 15, x = 15$"
      ],
      "answer": "$x = -15$",
      "points": 25
    },
    {
      "id": 194,
      "wave": 4,
      "question": "Solve for $y$: $y^2 = 31y - 240$.",
      "choices": [
        "$y = 15, y = 16$",
        "$y = -15, y = -16$",
        "$y = 15, y = -16$",
        "$y = -15, y = 16$"
      ],
      "answer": "$y = 15, y = 16$",
      "points": 25
    },
    {
      "id": 195,
      "wave": 4,
      "question": "Solve for $z$: $2z^2 - 34z + 144 = 0$.",
      "choices": [
        "$z = 8, z = 9$",
        "$z = -8, z = -9$",
        "$z = 8, z = -9$",
        "$z = -8, z = 9$"
      ],
      "answer": "$z = 8, z = 9$",
      "points": 25
    },
    {
      "id": 196,
      "wave": 4,
      "question": "Solve for $a$: $a^3 - 5a^2 - 4a + 20 = 0$.",
      "choices": [
        "$a = 5, a = 2, a = -2$",
        "$a = -5, a = 2, a = -2$",
        "$a = 5, a = 2$",
        "$a = 5, a = -2$"
      ],
      "answer": "$a = 5, a = 2, a = -2$",
      "points": 25
    },
    {
      "id": 197,
      "wave": 4,
      "question": "Solve for $b$: $b^2 + 31b = -240$.",
      "choices": [
        "$b = -15, b = -16$",
        "$b = 15, b = 16$",
        "$b = -15, b = 16$",
        "$b = 15, b = -16$"
      ],
      "answer": "$b = -15, b = -16$",
      "points": 25
    },
    {
      "id": 198,
      "wave": 4,
      "question": "Solve for $c$: $c^2 = 32c - 256$.",
      "choices": [
        "$c = 16$",
        "$c = -16$",
        "$c = 16, c = 16$",
        "$c = -16, c = -16$"
      ],
      "answer": "$c = 16$",
      "points": 25
    },
    {
      "id": 199,
      "wave": 4,
      "question": "Solve for $d$: $3d^2 - 45d + 168 = 0$.",
      "choices": [
        "$d = 7, d = 8$",
        "$d = -7, d = -8$",
        "$d = 7, d = -8$",
        "$d = -7, d = 8$"
      ],
      "answer": "$d = 7, d = 8$",
      "points": 25
    },
    {
      "id": 200,
      "wave": 4,
      "question": "Solve for $e$: $e^3 + 4e^2 - 16e - 64 = 0$.",
      "choices": [
        "$e = -4, e = 4$",
        "$e = 4$",
        "$e = -4$",
        "$e = -4, e = 4, e = 4$"
      ],
      "answer": "$e = -4, e = 4$",
      "points": 25
    },
    {
      "id": 201,
      "wave": 5,
      "question": "Solve for $x$: $x^3 + x^2 - 4x - 4 = 0$.",
      "choices": [
        "$x = -1, x = 2, x = -2$",
        "$x = 1, x = 2, x = -2$",
        "$x = -1, x = 2$",
        "$x = -1, x = -2$"
      ],
      "answer": "$x = -1, x = 2, x = -2$",
      "points": 30
    },
    {
      "id": 202,
      "wave": 5,
      "question": "Solve for $y$: $2y^3 - 8y^2 + 18y - 72 = 0$.",
      "choices": [
        "$y = 4$",
        "$y = -4$",
        "$y = 4, y = \\pm 3i$",
        "$y = -4, y = \\pm 3i$"
      ],
      "answer": "$y = 4$",
      "points": 30
    },
    {
      "id": 203,
      "wave": 5,
      "question": "Solve for $a$: $3a^2 - 3a - 36 = 0$.",
      "choices": [
        "$a = 4, a = -3$",
        "$a = -4, a = 3$",
        "$a = 4, a = 3$",
        "$a = -4, a = -3$"
      ],
      "answer": "$a = 4, a = -3$",
      "points": 30
    },
    {
      "id": 204,
      "wave": 5,
      "question": "Solve for $b$: $5b^2 - 50b + 125 = 0$.",
      "choices": ["$b = 5$", "$b = -5$", "$b = 5, b = 5$", "$b = -5, b = -5$"],
      "answer": "$b = 5$",
      "points": 30
    },
    {
      "id": 205,
      "wave": 5,
      "question": "Solve for $c$: $2x^2 + 20x + 48 = 0$.",
      "choices": [
        "$x = -4, x = -6$",
        "$x = 4, x = 6$",
        "$x = -4, x = 6$",
        "$x = 4, x = -6$"
      ],
      "answer": "$x = -4, x = -6$",
      "points": 30
    },
    {
      "id": 206,
      "wave": 5,
      "question": "Solve for $x$: $x^3 + 4x^2 - 9x - 36 = 0$.",
      "choices": [
        "$x = -4, x = 3, x = -3$",
        "$x = 4, x = 3, x = -3$",
        "$x = -4, x = 3$",
        "$x = -4, x = -3$"
      ],
      "answer": "$x = -4, x = 3, x = -3$",
      "points": 30
    },
    {
      "id": 207,
      "wave": 5,
      "question": "Solve for $y$: $y^2 = 33y - 270$.",
      "choices": [
        "$y = 15, y = 18$",
        "$y = -15, y = -18$",
        "$y = 15, y = -18$",
        "$y = -15, y = 18$"
      ],
      "answer": "$y = 15, y = 18$",
      "points": 30
    },
    {
      "id": 208,
      "wave": 5,
      "question": "Solve for $m$: $m^2 + 34m + 289 = 0$.",
      "choices": [
        "$m = -17$",
        "$m = 17$",
        "$m = -17, m = -17$",
        "$m = 17, m = 17$"
      ],
      "answer": "$m = -17$",
      "points": 30
    },
    {
      "id": 209,
      "wave": 5,
      "question": "Solve for $n$: $4n^2 - 52n + 168 = 0$.",
      "choices": [
        "$n = 6, n = 7$",
        "$n = -6, n = -7$",
        "$n = 6, n = -7$",
        "$n = -6, n = 7$"
      ],
      "answer": "$n = 6, n = 7$",
      "points": 30
    },
    {
      "id": 210,
      "wave": 5,
      "question": "Solve for $p$: $p^3 + 5p^2 - 4p - 20 = 0$.",
      "choices": [
        "$p = -5, p = 2, p = -2$",
        "$p = 5, p = 2, p = -2$",
        "$p = -5, p = 2$",
        "$p = -5, p = -2$"
      ],
      "answer": "$p = -5, p = 2, p = -2$",
      "points": 30
    },
    {
      "id": 211,
      "wave": 5,
      "question": "Solve for $q$: $q^2 + 35q = -300$.",
      "choices": [
        "$q = -15, q = -20$",
        "$q = 15, q = 20$",
        "$q = -15, q = 20$",
        "$q = 15, q = -20$"
      ],
      "answer": "$q = -15, q = -20$",
      "points": 30
    },
    {
      "id": 212,
      "wave": 5,
      "question": "Solve for $r$: $r^2 = 36r - 324$.",
      "choices": [
        "$r = 18$",
        "$r = -18$",
        "$r = 18, r = 18$",
        "$r = -18, r = -18$"
      ],
      "answer": "$r = 18$",
      "points": 30
    },
    {
      "id": 213,
      "wave": 5,
      "question": "Solve for $s$: $6s^2 - 66s + 180 = 0$.",
      "choices": [
        "$s = 5, s = 6$",
        "$s = -5, s = -6$",
        "$s = 5, s = -6$",
        "$s = -5, s = 6$"
      ],
      "answer": "$s = 5, s = 6$",
      "points": 30
    },
    {
      "id": 214,
      "wave": 5,
      "question": "Solve for $t$: $t^2 + 36t + 324 = 0$.",
      "choices": [
        "$t = -18$",
        "$t = 18$",
        "$t = -18, t = -18$",
        "$t = 18, t = 18$"
      ],
      "answer": "$t = -18$",
      "points": 30
    },
    {
      "id": 215,
      "wave": 5,
      "question": "Solve for $u$: $u^3 - 6u^2 - 9u + 54 = 0$.",
      "choices": [
        "$u = 6, u = 3, u = -3$",
        "$u = -6, u = 3, u = -3$",
        "$u = 6, u = 3$",
        "$u = 6, u = -3$"
      ],
      "answer": "$u = 6, u = 3, u = -3$",
      "points": 30
    },
    {
      "id": 216,
      "wave": 5,
      "question": "Solve for $v$: $v^2 + 37v = -342$.",
      "choices": [
        "$v = -18, v = -19$",
        "$v = 18, v = 19$",
        "$v = -18, v = 19$",
        "$v = 18, v = -19$"
      ],
      "answer": "$v = -18, v = -19$",
      "points": 30
    },
    {
      "id": 217,
      "wave": 5,
      "question": "Solve for $w$: $w^2 = 38w - 361$.",
      "choices": [
        "$w = 19$",
        "$w = -19$",
        "$w = 19, w = 19$",
        "$w = -19, w = -19$"
      ],
      "answer": "$w = 19$",
      "points": 30
    },
    {
      "id": 218,
      "wave": 5,
      "question": "Solve for $x$: $2x^2 - 36x + 162 = 0$.",
      "choices": ["$x = 9$", "$x = -9$", "$x = 9, x = 9$", "$x = -9, x = -9$"],
      "answer": "$x = 9$",
      "points": 30
    },
    {
      "id": 219,
      "wave": 5,
      "question": "Solve for $y$: $y^3 + 6y^2 - 4y - 24 = 0$.",
      "choices": [
        "$y = -6, y = 2, y = -2$",
        "$y = 6, y = 2, y = -2$",
        "$y = -6, y = 2$",
        "$y = -6, y = -2$"
      ],
      "answer": "$y = -6, y = 2, y = -2$",
      "points": 30
    },
    {
      "id": 220,
      "wave": 5,
      "question": "Solve for $z$: $z^2 + 39z = -380$.",
      "choices": [
        "$z = -19, z = -20$",
        "$z = 19, z = 20$",
        "$z = -19, z = 20$",
        "$z = 19, z = -20$"
      ],
      "answer": "$z = -19, z = -20$",
      "points": 30
    },
    {
      "id": 221,
      "wave": 5,
      "question": "Solve for $a$: $a^2 = 40a - 400$.",
      "choices": [
        "$a = 20$",
        "$a = -20$",
        "$a = 20, a = 20$",
        "$a = -20, a = -20$"
      ],
      "answer": "$a = 20$",
      "points": 30
    },
    {
      "id": 222,
      "wave": 5,
      "question": "Solve for $b$: $3b^2 - 48b + 192 = 0$.",
      "choices": ["$b = 8$", "$b = -8$", "$b = 8, b = 8$", "$b = -8, b = -8$"],
      "answer": "$b = 8$",
      "points": 30
    },
    {
      "id": 223,
      "wave": 5,
      "question": "Solve for $c$: $c^3 - 7c^2 - 4c + 28 = 0$.",
      "choices": [
        "$c = 7, c = 2, c = -2$",
        "$c = -7, c = 2, c = -2$",
        "$c = 7, c = 2$",
        "$c = 7, c = -2$"
      ],
      "answer": "$c = 7, c = 2, c = -2$",
      "points": 30
    },
    {
      "id": 224,
      "wave": 5,
      "question": "Solve for $d$: $d^2 + 40d = -400$.",
      "choices": [
        "$d = -20$",
        "$d = 20$",
        "$d = -20, d = -20$",
        "$d = 20, d = 20$"
      ],
      "answer": "$d = -20$",
      "points": 30
    },
    {
      "id": 225,
      "wave": 5,
      "question": "Solve for $e$: $e^2 = 41e - 420$.",
      "choices": [
        "$e = 20, e = 21$",
        "$e = -20, e = -21$",
        "$e = 20, e = -21$",
        "$e = -20, e = 21$"
      ],
      "answer": "$e = 20, e = 21$",
      "points": 30
    },
    {
      "id": 226,
      "wave": 5,
      "question": "Solve for $f$: $4f^2 - 60f + 225 = 0$.",
      "choices": [
        "$f = 7.5$",
        "$f = -7.5$",
        "$f = 7.5, f = 7.5$",
        "$f = -7.5, f = -7.5$"
      ],
      "answer": "$f = 7.5$",
      "points": 30
    },
    {
      "id": 227,
      "wave": 5,
      "question": "Solve for $g$: $g^3 + 7g^2 - 4g - 28 = 0$.",
      "choices": [
        "$g = -7, g = 2, g = -2$",
        "$g = 7, g = 2, g = -2$",
        "$g = -7, g = 2$",
        "$g = -7, g = -2$"
      ],
      "answer": "$g = -7, g = 2, g = -2$",
      "points": 30
    },
    {
      "id": 228,
      "wave": 5,
      "question": "Solve for $h$: $h^2 + 41h = -420$.",
      "choices": [
        "$h = -20, h = -21$",
        "$h = 20, h = 21$",
        "$h = -20, h = 21$",
        "$h = 20, h = -21$"
      ],
      "answer": "$h = -20, h = -21$",
      "points": 30
    },
    {
      "id": 229,
      "wave": 5,
      "question": "Solve for $i$: $i^2 = 42i - 441$.",
      "choices": [
        "$i = 21$",
        "$i = -21$",
        "$i = 21, i = 21$",
        "$i = -21, i = -21$"
      ],
      "answer": "$i = 21$",
      "points": 30
    },
    {
      "id": 230,
      "wave": 5,
      "question": "Solve for $j$: $5j^2 - 70j + 245 = 0$.",
      "choices": ["$j = 7$", "$j = -7$", "$j = 7, j = 7$", "$j = -7, j = -7$"],
      "answer": "$j = 7$",
      "points": 30
    },
    {
      "id": 231,
      "wave": 5,
      "question": "Solve for $k$: $k^3 - 8k^2 - 9k + 72 = 0$.",
      "choices": [
        "$k = 8, k = 3, k = -3$",
        "$k = -8, k = 3, k = -3$",
        "$k = 8, k = 3$",
        "$k = 8, k = -3$"
      ],
      "answer": "$k = 8, k = 3, k = -3$",
      "points": 30
    },
    {
      "id": 232,
      "wave": 5,
      "question": "Solve for $l$: $l^2 + 42l = -441$.",
      "choices": [
        "$l = -21$",
        "$l = 21$",
        "$l = -21, l = -21$",
        "$l = 21, l = 21$"
      ],
      "answer": "$l = -21$",
      "points": 30
    },
    {
      "id": 233,
      "wave": 5,
      "question": "Solve for $m$: $m^2 = 43m - 462$.",
      "choices": [
        "$m = 21, m = 22$",
        "$m = -21, m = -22$",
        "$m = 21, m = -22$",
        "$m = -21, m = 22$"
      ],
      "answer": "$m = 21, m = 22$",
      "points": 30
    },
    {
      "id": 234,
      "wave": 5,
      "question": "Solve for $n$: $2n^2 - 44n + 242 = 0$.",
      "choices": [
        "$n = 11$",
        "$n = -11$",
        "$n = 11, n = 11$",
        "$n = -11, n = -11$"
      ],
      "answer": "$n = 11$",
      "points": 30
    },
    {
      "id": 235,
      "wave": 5,
      "question": "Solve for $p$: $p^3 + 8p^2 - 4p - 32 = 0$.",
      "choices": [
        "$p = -8, p = 2, p = -2$",
        "$p = 8, p = 2, p = -2$",
        "$p = -8, p = 2$",
        "$p = -8, p = -2$"
      ],
      "answer": "$p = -8, p = 2, p = -2$",
      "points": 30
    },
    {
      "id": 236,
      "wave": 5,
      "question": "Solve for $q$: $q^2 + 43q = -462$.",
      "choices": [
        "$q = -21, q = -22$",
        "$q = 21, q = 22$",
        "$q = -21, q = 22$",
        "$q = 21, q = -22$"
      ],
      "answer": "$q = -21, q = -22$",
      "points": 30
    },
    {
      "id": 237,
      "wave": 5,
      "question": "Solve for $r$: $r^2 = 44r - 484$.",
      "choices": [
        "$r = 22$",
        "$r = -22$",
        "$r = 22, r = 22$",
        "$r = -22, r = -22$"
      ],
      "answer": "$r = 22$",
      "points": 30
    },
    {
      "id": 238,
      "wave": 5,
      "question": "Solve for $s$: $3s^2 - 51s + 216 = 0$.",
      "choices": [
        "$s = 8, s = 9$",
        "$s = -8, s = -9$",
        "$s = 8, s = -9$",
        "$s = -8, s = 9$"
      ],
      "answer": "$s = 8, s = 9$",
      "points": 30
    },
    {
      "id": 239,
      "wave": 5,
      "question": "Solve for $t$: $t^3 - 9t^2 - 4t + 36 = 0$.",
      "choices": [
        "$t = 9, t = 2, t = -2$",
        "$t = -9, t = 2, t = -2$",
        "$t = 9, t = 2$",
        "$t = 9, t = -2$"
      ],
      "answer": "$t = 9, t = 2, t = -2$",
      "points": 30
    },
    {
      "id": 240,
      "wave": 5,
      "question": "Solve for $u$: $u^2 + 45u = -500$.",
      "choices": [
        "$u = -20, u = -25$",
        "$u = 20, u = 25$",
        "$u = -20, u = 25$",
        "$u = 20, u = -25$"
      ],
      "answer": "$u = -20, u = -25$",
      "points": 30
    },
    {
      "id": 241,
      "wave": 5,
      "question": "Solve for $v$: $v^2 = 46v - 529$.",
      "choices": [
        "$v = 23$",
        "$v = -23$",
        "$v = 23, v = 23$",
        "$v = -23, v = -23$"
      ],
      "answer": "$v = 23$",
      "points": 30
    },
    {
      "id": 242,
      "wave": 5,
      "question": "Solve for $w$: $4w^2 - 68w + 289 = 0$.",
      "choices": [
        "$w = 8.5$",
        "$w = -8.5$",
        "$w = 8.5, w = 8.5$",
        "$w = -8.5, w = -8.5$"
      ],
      "answer": "$w = 8.5$",
      "points": 30
    },
    {
      "id": 243,
      "wave": 5,
      "question": "Solve for $x$: $x^3 + 9x^2 - 4x - 36 = 0$.",
      "choices": [
        "$x = -9, x = 2, x = -2$",
        "$x = 9, x = 2, x = -2$",
        "$x = -9, x = 2$",
        "$x = -9, x = -2$"
      ],
      "answer": "$x = -9, x = 2, x = -2$",
      "points": 30
    },
    {
      "id": 244,
      "wave": 5,
      "question": "Solve for $y$: $y^2 + 47y = -550$.",
      "choices": [
        "$y = -22, y = -25$",
        "$y = 22, y = 25$",
        "$y = -22, y = 25$",
        "$y = 22, y = -25$"
      ],
      "answer": "$y = -22, y = -25$",
      "points": 30
    },
    {
      "id": 245,
      "wave": 5,
      "question": "Solve for $z$: $z^2 = 48z - 576$.",
      "choices": [
        "$z = 24$",
        "$z = -24$",
        "$z = 24, z = 24$",
        "$z = -24, z = -24$"
      ],
      "answer": "$z = 24$",
      "points": 30
    },
    {
      "id": 246,
      "wave": 5,
      "question": "Solve for $a$: $5a^2 - 80a + 320 = 0$.",
      "choices": ["$a = 8$", "$a = -8$", "$a = 8, a = 8$", "$a = -8, a = -8$"],
      "answer": "$a = 8$",
      "points": 30
    },
    {
      "id": 247,
      "wave": 5,
      "question": "Solve for $b$: $b^3 - 10b^2 - 4b + 40 = 0$.",
      "choices": [
        "$b = 10, b = 2, b = -2$",
        "$b = -10, b = 2, b = -2$",
        "$b = 10, b = 2$",
        "$b = 10, b = -2$"
      ],
      "answer": "$b = 10, b = 2, b = -2$",
      "points": 30
    },
    {
      "id": 248,
      "wave": 5,
      "question": "Solve for $c$: $c^2 + 49c = -600$.",
      "choices": [
        "$c = -24, c = -25$",
        "$c = 24, c = 25$",
        "$c = -24, c = 25$",
        "$c = 24, c = -25$"
      ],
      "answer": "$c = -24, c = -25$",
      "points": 30
    },
    {
      "id": 249,
      "wave": 5,
      "question": "Solve for $d$: $d^2 = 50d - 625$.",
      "choices": [
        "$d = 25$",
        "$d = -25$",
        "$d = 25, d = 25$",
        "$d = -25, d = -25$"
      ],
      "answer": "$d = 25$",
      "points": 30
    },
    {
      "id": 250,
      "wave": 5,
      "question": "Solve for $e$: $2e^2 - 50e + 312.5 = 0$.",
      "choices": [
        "$e = 12.5$",
        "$e = -12.5$",
        "$e = 12.5, e = 12.5$",
        "$e = -12.5, e = -12.5$"
      ],
      "answer": "$e = 12.5$",
      "points": 30
    }
  ]
}
